Workbook

Sheet Nómina mensual
B2: Nómina mensual 2026 | I2: El sindicato de la enseñanza pública
B3: Elaborado por Manuel Pérez García. Secretario de Acción Sindical de ANPE ANDALUCÍA
B5: Cuerpo Docente | C5: 590-Profesores Enseñanza Secundaria | G5: Grupo prof: | H5: =IF($C$5="597-Maestros","A2",IF($C$5="596-Maestros de Taller de Artes Plásticas y Diseño","A2",IF($C$5="591-Profesores Técnicos de Formación Profesional","A2","A1"))) -> A1
B6: Funcionario | C6: Carrera | E6: Seleccionar en celdas sombreadas
B7: Años de Servicio | C7: 5
B8: Maestro de 1º y 2º de la ESO | C8: NO
B9: Nómina con Paga Extraordinaria | C9: NO | G9: Baleares
B10: Destino en Isla No Capitalina (Canarias) | C10: SI | G10: Elige Isla | H10: Formentera
B11: Tutor | C11: SI
B12: Cargo directivo | C12: Vicedirección
B13: Tipo de centro | C13: C
B14: % de retención de IRPF | C14: 0.24
B15: RETRIBUCIONES
C16: Andalucía | D16: Aragón | E16: Asturias | F16: Baleares (Islas) | G16: Canarias | H16: Cantabria | I16: Castilla La Mancha | J16: Castilla y León | K16: Cataluña | L16: Extremadura | M16: Galicia | N16: La Rioja | O16: Madrid | P16: Murcia | Q16: Valencia | R16: Ceuta y Melilla | S16: País Vasco | T16: Navarra
B17: Sueldo Base | C17: =+AD80 -> 1387.24 | D17: =+AE80 -> 1387.24 | E17: =+AF80 -> 1387.24 | F17: =+AG80 -> 1387.24 | G17: =+AC80 -> 1387.24 | H17: =+AH80 -> 1387.24 | I17: =+AI80 -> 1387.24 | J17: =+AJ80 -> 1387.24 | K17: =+AK80 -> 1387.24 | L17: =+AL80 -> 1387.24 | M17: =+AM80 -> 1387.24 | N17: =+AN80 -> 1387.24 | O17: =+AO80 -> 1387.24 | ... T17: =+AT80 -> 2258.75 | U17: Sueldo Base
B18: Trienios | C18: =AD82*INT($C$7/3) -> 53.39 | D18: =AE82*INT($C$7/3) -> 53.39 | E18: =AF82*INT($C$7/3) -> 53.39 | F18: =AG82*INT($C$7/3) -> 53.39 | G18: =IF($C$10="NO",AC82*INT($C$7/3),0) -> 0 | H18: =AH82*INT($C$7/3) -> 53.39 | I18: =AI82*INT($C$7/3) -> 53.39 | J18: =AJ82*INT($C$7/3) -> 53.39 | K18: =AK82*INT($C$7/3) -> 53.39 | L18: =AL82*INT($C$7/3) -> 53.39 | M18: =AM82*INT($C$7/3) -> 53.39 | N18: =AN82*INT($C$7/3) -> 53.39 | O18: =AO82*INT($C$7/3) -> 53.39 | ... S18: =AS82*INT($C$7/3) -> 53.39 | T18: =+AT95 -> 24.15 | U18: ANTIGÜEDAD NAVARRA
B19: Complemento Destino | C19: =+AD84 -> 729.14 | D19: =+AE84 -> 729.14 | E19: =+AF84 -> 736.54 | F19: =+AG84 -> 718.36 | G19: =+AC84 -> 728.32 | H19: =+AH84 -> 767.49 | I19: =+AI84 -> 729.14 | J19: =+AJ84 -> 729.14 | K19: =+AK84 -> 729.14 | L19: =+AL84 -> 729.14 | M19: =+AM84 -> 729.14 | N19: =+AN84 -> 729.14 | O19: =+AO84 -> 729.14 | ... T19: =+AT84 -> 0
B20: Complemento Específico General | C20: =+AD85 -> 881.46 | D20: =+AE85 -> 756.22 | E20: =+AF85 -> 708.37 | F20: =+AG85 -> 450.98 | G20: =+AC85 -> 757.35 | H20: =+AH85 -> 875.1 | I20: =+AI85 -> 282 | J20: =+AJ85 -> 294.2 | K20: =+AK85 -> 720.83 | L20: =+AL85 -> 520.73 | M20: =+AM85 -> 779.29 | N20: =+AN85 -> 909.64 | O20: =+AO85 -> 798.41 | ... T20: =+AT85 -> 756.23 | U20: Complemento Específico
B21: Complemento Específico Autonómico | C21: =+AD86 -> 0 | E21: =+AF86 -> 0 | F21: =+AG86 -> 429.57 | H21: =+AH86 -> 0 | I21: =+AI86 -> 585.97 | J21: =+AJ86 -> 424.79 | K21: =+AK86 -> 0 | L21: =+AL86 -> 181.99 | M21: =+AM86 -> 0 | N21: =+AN86 -> 0 | O21: =+AO86 -> 0 | ... R21: =+AR86 -> 0 | T21: =+AT86 -> 0
B22: Sin Sexenio | E22: =IF($C$7<6,+AF87,0) -> 113.85 | F22: =+AG87 -> 0 | H22: =IF($C$7<6,AH87,0) -> 35.77 | P22: =+AP87 -> 0 | U22: 5 años
B23: 1º Sexenio | C23: =IF($C$7>5,AD88,0) -> 0 | D23: =IF($C$7>5,AE88,0) -> 0 | E23: =IF($C$7>5,AF88,0) -> 0 | F23: =IF($C$7>5,AG88,0) -> 0 | G23: =IF($C$7>5,AC88,0) -> 0 | H23: =IF($C$7>5,AH88,0) -> 0 | I23: =IF($C$7>5,AI88,0) -> 0 | J23: =IF($C$7>5,AJ88,0) -> 0 | K23: =IF($C$7>5,AK88,0) -> 0 | L23: =IF($C$7>5,AL88,0) -> 0 | M23: =IF($C$7>5,AM88,0) -> 0 | N23: =IF($C$7>5,AN88,0) -> 0 | O23: =IF($C$7>5,AO88,0) -> 0 | ... S23: =IF($C$7>5,AS88,0) -> 0 | U23: 6 años y 7 meses
B24: 2º Sexenio | C24: =IF($C$7>11,AD89,0) -> 0 | D24: =IF($C$7>11,AE89,0) -> 0 | E24: =IF($C$7>11,AF89,0) -> 0 | F24: =IF($C$7>11,AG89,0) -> 0 | G24: =IF($C$7>11,AC89,0) -> 0 | H24: =IF($C$7>11,AH89,0) -> 0 | I24: =IF($C$7>11,AI89,0) -> 0 | J24: =IF($C$7>11,AJ89,0) -> 0 | K24: =IF($C$7>11,AK89,0) -> 0 | L24: =IF($C$7>11,AL89,0) -> 0 | M24: =IF($C$7>11,AM89,0) -> 0 | N24: =IF($C$7>11,AN89,0) -> 0 | O24: =IF($C$7>11,AO89,0) -> 0 | ... S24: =IF($C$7>11,AS89,0) -> 0 | U24: 10 años
B25: 3º Sexenio | C25: =IF($C$7>17,AD90,0) -> 0 | D25: =IF($C$7>17,AE90,0) -> 0 | E25: =IF($C$7>17,AF90,0) -> 0 | F25: =IF($C$7>17,AG90,0) -> 0 | G25: =IF($C$7>17,AC90,0) -> 0 | H25: =IF($C$7>17,AH90,0) -> 0 | I25: =IF($C$7>17,AI90,0) -> 0 | J25: =IF($C$7>17,AJ90,0) -> 0 | K25: =IF($C$7>17,AK90,0) -> 0 | L25: =IF($C$7>17,AL90,0) -> 0 | M25: =IF($C$7>17,AM90,0) -> 0 | N25: =IF($C$7>17,AN90,0) -> 0 | O25: =IF($C$7>17,AO90,0) -> 0 | ... S25: =IF($C$7>17,AS90,0) -> 0 | U25: 13 años y 2 meses
B26: 4º Sexenio | C26: =IF($C$7>23,AD91,0) -> 0 | D26: =IF($C$7>23,AE91,0) -> 0 | E26: =IF($C$7>23,AF91,0) -> 0 | F26: =IF($C$7>23,AG91,0) -> 0 | G26: =IF($C$7>23,AC91,0) -> 0 | H26: =IF($C$7>23,AH91,0) -> 0 | I26: =IF($C$7>23,AI91,0) -> 0 | J26: =IF($C$7>23,AJ91,0) -> 0 | K26: =IF($C$7>23,AK91,0) -> 0 | L26: =IF($C$7>23,AL91,0) -> 0 | M26: =IF($C$7>23,AM91,0) -> 0 | N26: =IF($C$7>23,AN91,0) -> 0 | O26: =IF($C$7>23,AO91,0) -> 0 | ... S26: =IF($C$7>23,AS91,0) -> 0 | U26: 15 años
B27: 5º Sexenio | C27: =IF($C$7>29,AD92,0) -> 0 | D27: =IF($C$7>29,AE92,0) -> 0 | E27: =IF($C$7>29,AF92,0) -> 0 | F27: =IF($C$7>29,AG92,0) -> 0 | G27: =IF($C$7>29,AC92,0) -> 0 | H27: =IF($C$7>29,AH92,0) -> 0 | I27: =IF($C$7>29,AI92,0) -> 0 | J27: =IF($C$7>29,AJ92,0) -> 0 | K27: =IF($C$7>29,AK92,0) -> 0 | L27: =IF($C$7>29,AL92,0) -> 0 | M27: =IF($C$7>29,AM92,0) -> 0 | N27: =IF($C$7>29,AN92,0) -> 0 | O27: =IF($C$7>29,AO92,0) -> 0 | ... S27: =IF($C$7>29,AS92,0) -> 0 | U27: 19 años y 9 meses
B28: =IF(C11="si","Tutoría"," ") -> Tutoría | C28: =IF($C$11="si",AD93," ") -> 31.97 | D28: =IF($C$11="si",AE93," ") -> 0 | E28: =IF($C$11="si",AF93," ") -> 0 | F28: =IF($C$11="si",AG93," ") -> 36.71 | G28: =IF($C$11="si",AC93," ") -> 35 | H28: =IF($C$11="si",AH93," ") -> 0 | I28: =IF($C$11="si",AI93," ") -> 0 | J28: =IF($C$11="si",AJ93," ") -> 0 | K28: =IF($C$11="si",AK93," ") -> 93.6 | L28: =IF($C$11="si",AL93," ") -> 47.72 | M28: =IF($C$11="si",AM93," ") -> 66.04 | N28: =IF($C$11="si",AN93," ") -> 0 | O28: =IF($C$11="si",AO93," ") -> 70.94 | ... S28: =IF($C$11="si",AS93," ") -> 62.45 | U28: 20 años
B29: Cargo directivo | C29: =IF($H$5="A1",INDEX(Retribuciones!W53:AA58,MATCH($C$13,Retribuciones!Q53:Q58,0),MATCH($C$12,Retribuciones!W52:AA52,0)),INDEX(Retribuciones!R53:V58,MATCH($C$13,Retribuciones!Q53:Q58,0),MATCH($C$12,Retribuciones!R52:V52,0))) -> 350.9 | D29: =IF($H$5="A1",INDEX(Retribuciones!W89:AA94,MATCH($C$13,Retribuciones!Q89:Q94,0),MATCH($C$12,Retribuciones!W88:AA88,0)),INDEX(Retribuciones!R89:V94,MATCH($C$13,Retribuciones!Q89:Q94,0),MATCH($C$12,Retribuciones!R88:V88,0))) -> 332.96 | E29: =IF($H$5="A1",INDEX(Retribuciones!W125:AA130,MATCH($C$13,Retribuciones!Q125:Q130,0),MATCH($C$12,Retribuciones!W124:AA124,0)),INDEX(Retribuciones!R125:V130,MATCH($C$13,Retribuciones!Q125:Q130,0),MATCH($C$12,Retribuciones!R124:V124,0))) -> 0 | F29: =IF($H$5="A1",INDEX(Retribuciones!W161:AA166,MATCH($C$13,Retribuciones!Q161:Q166,0),MATCH($C$12,Retribuciones!W160:AA160,0)),INDEX(Retribuciones!R161:V166,MATCH($C$13,Retribuciones!Q161:Q166,0),MATCH($C$12,Retribuciones!R160:V160,0))) -> 0 | G29: =IF($H$5="A1",INDEX(Retribuciones!W13:AA18,MATCH($C$13,Retribuciones!Q13:Q18,0),MATCH($C$12,Retribuciones!W12:AA12,0)),INDEX(Retribuciones!R13:V18,MATCH($C$13,Retribuciones!Q13:Q18,0),MATCH($C$12,Retribuciones!R12:V12,0))) -> 253.88 | H29: =IF($H$5="A1",INDEX(Retribuciones!W197:AA202,MATCH($C$13,Retribuciones!Q197:Q202,0),MATCH($C$12,Retribuciones!W196:AA196,0)),INDEX(Retribuciones!R197:V197,MATCH($C$13,Retribuciones!Q197:Q202,0),MATCH($C$12,Retribuciones!R196:V196,0))) -> 410.05 | I29: =IF($H$5="A1",INDEX(Retribuciones!W233:AA238,MATCH($C$13,Retribuciones!Q233:Q238,0),MATCH($C$12,Retribuciones!W232:AA232,0)),INDEX(Retribuciones!R233:V238,MATCH($C$13,Retribuciones!Q233:Q238,0),MATCH($C$12,Retribuciones!R232:V232,0))) -> 0 | J29: =IF($H$5="A1",INDEX(Retribuciones!W269:AA274,MATCH($C$13,Retribuciones!Q269:Q274,0),MATCH($C$12,Retribuciones!W268:AA268,0)),INDEX(Retribuciones!R269:V274,MATCH($C$13,Retribuciones!Q269:Q274,0),MATCH($C$12,Retribuciones!R268:V268,0))) -> 0 | K29: =IF($H$5="A1",INDEX(Retribuciones!W305:AA310,MATCH($C$13,Retribuciones!Q305:Q310,0),MATCH($C$12,Retribuciones!W304:AA304,0)),INDEX(Retribuciones!R305:V310,MATCH($C$13,Retribuciones!Q305:Q310,0),MATCH($C$12,Retribuciones!R304:V304,0))) -> 0 | L29: =IF($H$5="A1",INDEX(Retribuciones!W341:AA346,MATCH($C$13,Retribuciones!Q341:Q346,0),MATCH($C$12,Retribuciones!W340:AA340,0)),INDEX(Retribuciones!R341:V346,MATCH($C$13,Retribuciones!Q341:Q346,0),MATCH($C$12,Retribuciones!R340:V340,0))) -> 213.95 | M29: =IF($H$5="A1",INDEX(Retribuciones!W378:AA383,MATCH($C$13,Retribuciones!Q378:Q383,0),MATCH($C$12,Retribuciones!W377:AA377,0)),INDEX(Retribuciones!R378:V383,MATCH($C$13,Retribuciones!Q378:Q383,0),MATCH($C$12,Retribuciones!R377:V377,0))) -> 308.04 | N29: =IF($H$5="A1",INDEX(Retribuciones!W413:AA418,MATCH($C$13,Retribuciones!Q413:Q418,0),MATCH($C$12,Retribuciones!W412:AA412,0)),INDEX(Retribuciones!R413:V418,MATCH($C$13,Retribuciones!Q413:Q418,0),MATCH($C$12,Retribuciones!R412:V412,0))) -> 0 | O29: =IF($H$5="A1",INDEX(Retribuciones!W449:AA454,MATCH($C$13,Retribuciones!Q449:Q454,0),MATCH($C$12,Retribuciones!W448:AA448,0)),INDEX(Retribuciones!R449:V454,MATCH($C$13,Retribuciones!Q449:Q454,0),MATCH($C$12,Retribuciones!R448:V448,0))) -> 596.262 | P29: =IF($H$5="A1",INDEX(Retribuciones!W485:AA490,MATCH($C$13,Retribuciones!Q485:Q490,0),MATCH($C$12,Retribuciones!W484:AA484,0)),INDEX(Retribuciones!R485:V490,MATCH($C$13,Retribuciones!Q485:Q490,0),MATCH($C$12,Retribuciones!R484:V484,0))) -> 0 | Q29: =IF($H$5="A1",INDEX(Retribuciones!W521:AA526,MATCH($C$13,Retribuciones!Q521:Q526,0),MATCH($C$12,Retribuciones!W520:AA520,0)),INDEX(Retribuciones!R521:V526,MATCH($C$13,Retribuciones!Q521:Q526,0),MATCH($C$12,Retribuciones!R520:V520,0))) -> 483.99 | R29: =IF($H$5="A1",INDEX(Retribuciones!W557:AA562,MATCH($C$13,Retribuciones!Q557:Q562,0),MATCH($C$12,Retribuciones!W556:AA556,0)),INDEX(Retribuciones!R557:V562,MATCH($C$13,Retribuciones!Q557:Q562,0),MATCH($C$12,Retribuciones!R556:V556,0))) -> 0 | S29: =IF($H$5="A1",INDEX(Retribuciones!W593:AA598,MATCH($C$13,Retribuciones!Q593:Q598,0),MATCH($C$12,Retribuciones!W592:AA592,0)),INDEX(Retribuciones!R593:V598,MATCH($C$13,Retribuciones!Q593:Q598,0),MATCH($C$12,Retribuciones!R592:V592,0))) -> 0 | T29: =IF($H$5="A1",INDEX(Retribuciones!W629:AA634,MATCH($C$13,Retribuciones!Q629:Q634,0),MATCH($C$12,Retribuciones!W628:AA628,0)),INDEX(Retribuciones!R629:V634,MATCH($C$13,Retribuciones!Q629:Q634,0),MATCH($C$12,Retribuciones!R628:V628,0))) -> 338.81
B30: Residencia | F30: =IF($H$10="Mallorca",AG94,AG95) -> 693.08 | G30: =IF($C$10="si",AC95,AC94) -> 534.9 | R30: =+AR95 -> 1102.57 | U30: 25 años
B31: Trienio Residencia | G31: =IF($C$10="si",AC96*INT($C$7/3)," ") -> 37.63 | R31: =AR94*INT($C$7/3) -> 66.76 | U31: 26 años y 4 meses
B32: Fondos adicionales/Especial dedicación/Carrera Docente | D32: =+AE98 -> 0 | E32: =IF($C$7>10,AF99,IF(AND($C$7>5,$C$7<11),AF98,0)) -> 0 | F32: =IF($C$7>12,+AG99,IF($C$7>6,+AG98,0)) -> 0 | J32: =+AJ98 -> 27.04 | L32: =+AL98 -> 0 | N32: =+AN98 -> 0 | U32: 30 años
B33: =IF(C8="si","Adicional maestros 1º y 2º ESO"," ") | C33: =IF($C$8="si",AD97," ") | D33: =IF($C$8="si",AE97," ") | E33: =IF($C$8="si",AF97," ") | F33: =IF($C$8="si",AG97," ") | G33: =IF($C$8="si",AC97," ") | H33: =IF($C$8="si",AH97," ") | I33: =IF($C$8="si",AI97," ") | J33: =IF($C$8="si",AJ97," ") | K33: =IF($C$8="si",AK97," ") | L33: =IF($C$8="si",AL97," ") | M33: =IF($C$8="si",AM97," ") | N33: =IF($C$8="si",AN97," ") | O33: =IF($C$8="si",AO97," ") | ... T33: =IF($C$8="si",AT97," ") | U33: 32 años y 11 meses
B34: =IF($C$9="si","Paga extra, Sueldo Base"," ") | C34: =IF($C$9="si",AD81," ") | D34: =IF($C$9="si",AE81," ") | E34: =IF($C$9="si",AF81," ") | F34: =IF($C$9="si",AG81," ") | G34: =IF($C$9="si",AC81," ") | H34: =IF($C$9="si",AH81," ") | I34: =IF($C$9="si",AI81," ") | J34: =IF($C$9="si",AJ81," ") | K34: =IF($C$9="si",AK81," ") | L34: =IF($C$9="si",AL81," ") | M34: =IF($C$9="si",AM81," ") | N34: =IF($C$9="si",AN81," ") | O34: =IF($C$9="si",AO81," ") | ... S34: =IF($C$9="si",AS81," ") | U34: 35 años
B35: =IF($C$9="si","Paga extra, Trienios"," ") | C35: =IF($C$9="si",AD83*INT($C$7/3)," ") | D35: =IF($C$9="si",AE83*INT($C$7/3)," ") | E35: =IF($C$9="si",AF83*INT($C$7/3)," ") | F35: =IF($C$9="si",AG83*INT($C$7/3)," ") | G35: =IF($C$9="si",AC83*INT($C$7/3)," ") | H35: =IF($C$9="si",AH83*INT($C$7/3)," ") | I35: =IF($C$9="si",AI83*INT($C$7/3)," ") | J35: =IF($C$9="si",AJ83*INT($C$7/3)," ") | K35: =IF($C$9="si",AK83*INT($C$7/3)," ") | L35: =IF($C$9="si",AL83*INT($C$7/3)," ") | M35: =IF($C$9="si",AM83*INT($C$7/3)," ") | N35: =IF($C$9="si",AN83*INT($C$7/3)," ") | O35: =IF($C$9="si",AO83*INT($C$7/3)," ") | ... S35: =IF($C$9="si",AS83*INT($C$7/3)," ") | U35: 40 años
B36: =IF($C$9="si","Paga extra, Complemento Destino"," ") | C36: =IF($C$9="si",AD84," ") | D36: =IF($C$9="si",AE84," ") | E36: =IF($C$9="si",AF84," ") | F36: =IF($C$9="si",AG84," ") | G36: =IF($C$9="si",AC84," ") | H36: =IF($C$9="si",AH84," ") | I36: =IF($C$9="si",AI84," ") | J36: =IF($C$9="si",AJ84," ") | K36: =IF($C$9="si",AK84," ") | L36: =IF($C$9="si",AL84," ") | M36: =IF($C$9="si",AM84," ") | N36: =IF($C$9="si",AN84," ") | O36: =IF($C$9="si",AO84," ") | ... S36: =IF($C$9="si",AS84," ") | T36: =IF($C$9="si",SUM(T17:T35),0) -> 0 | U36: < Extra Navarra
B37: =IF($C$9="si","Paga extra, Complemento Específico"," ") | C37: =IF($C$9="si",AD85," ") | E37: =IF($C$9="si",AF85," ") | F37: =IF($C$9="si",AG85," ") | G37: =IF($C$9="si",AC86," ") | H37: =IF($C$9="si",AH85," ") | I37: =IF($C$9="si",AI85," ") | J37: =IF($C$9="si",AJ85," ") | K37: =IF($C$9="si",AK85," ") | L37: =IF($C$9="si",AL85," ") | M37: =IF($C$9="si",AM85," ") | N37: =IF($C$9="si",AN85," ") | O37: =IF($C$9="si",AO85," ") | P37: =IF($C$9="si",AP85*70%," ") | Q37: =IF($C$9="si",AQ85," ") | R37: =IF($C$9="si",AR85," ") | S37: =IF($C$9="si",AS85," ") | T37: =IF($C$9="s",AT85*0.78," ")
B38: =IF($C$9="si","Paga extra, Complemento Específico Autonómico"," ") | C38: =IF($C$9="si",AD86," ") | D38: =IF($C$9="si",AE86," ") | E38: =IF($C$9="si",AF86," ") | F38: =IF($C$9="si",AG86," ") | H38: =IF($C$9="si",AH86," ") | I38: =IF($C$9="si",AI86," ") | J38: =IF($C$9="si",AJ86," ") | K38: =IF($C$9="si",AK86," ") | L38: =IF($C$9="si",AL86," ") | M38: =IF($C$9="si",AM86," ") | N38: =IF($C$9="si",AN86," ") | O38: =IF($C$9="si",AO86," ") | P38: =IF($C$9="si",AP86*60%," ") | Q38: =IF($C$9="si",AQ86," ") | R38: =IF($C$9="si",AR86," ") | S38: =IF($C$9="si",AS86," ") | T38: =IF($C$9="s",AT86*0.78," ")
B39: =IF($C$9="si","Paga extra, Complemento Sexenios"," ") | C39: =IF($C$9="si",SUM(C22:C27)," ") | D39: =IF($C$9="si",SUM(D22:D27)," ") | E39: =IF($C$9="si",SUM(E22:E27)," ") | F39: =IF($C$9="si",SUM(F22:F27)," ") | G39: =IF($C$9="si",SUM(G22:G27)," ") | H39: =IF($C$9="si",SUM(H22:H27)," ") | I39: =IF($C$9="si",SUM(I22:I27)," ") | J39: =IF($C$9="si",SUM(J22:J27)," ") | ... O39: =IF($C$9="si",SUM(O22:O27)," ") | P39: =IF($C$9="si",SUM(P23:P27)*64%," ") | Q39: =IF($C$9="si",SUM(Q22:Q27)," ") | R39: =IF($C$9="si",SUM(R22:R27)," ") | S39: =IF($C$9="si",SUM(S22:S27)," ") | T39: =IF($C$9="s",(T23+T24+T25+T26+T27)*0.78," ")
B40: =IF($C$9="si","Productividad semestral"," ") | C40: =IF($C$9="si",AD99," ") | D40: =IF($C$9="si",AE99," ") | F40: =IF($C$9="si",AG99," ") | G40: =IF($C$9="si",AC99," ") | H40: =IF($C$9="si",AH99," ") | I40: =IF($C$9="si",AI99," ") | J40: =IF($C$9="si",AJ99," ") | K40: =IF($C$9="si",AK99," ") | L40: =IF($C$9="si",AL99," ") | M40: =IF($C$9="si",AM99," ") | N40: =IF($C$9="si",AN99," ") | O40: =IF($C$9="si",AO99," ") | ... S40: =IF($C$9="si",AS99," ") | T40: =IF($C$9="s",AT99," ")
B41: SUELDO BRUTO MENSUAL | C41: =SUM(C17:C39) -> 3434.1 | D41: =SUM(D17:D40) -> 3258.95 | E41: =SUM(E17:E39) -> 2999.39 | F41: =SUM(F17:F39) -> 3769.33 | G41: =SUM(G17:G39) -> 3734.32 | H41: =SUM(H17:H39) -> 3529.04 | I41: =SUM(I17:I39) -> 3037.74 | J41: =SUM(J17:J39) -> 2915.8 | K41: =SUM(K17:K39) -> 2984.2 | L41: =SUM(L17:L39) -> 3134.16 | ... O41: =SUM(O17:O39) -> 3635.382 | P41: =SUM(P17:P40) -> 3047.55 | Q41: =SUM(Q17:Q39) -> 3384.76 | R41: =SUM(R17:R39) -> 3836.24 | S41: =SUM(S17:S39) -> 3355.04 | T41: =SUM(T17:T21)+T36 -> 3039.13
B43: DESCUENTOS
B44: =IF(C6=AA72,"MUFACE","Contingencias Comunes y MEI") -> MUFACE | C44: =IF($C$6="interino",-C56*4.82%,IF($C$9="si",2*AD102,AD102)) -> -51.68 | D44: =IF($C$6="interino",-D56*4.82%,IF($C$9="si",2*AE102,AE102)) -> -51.68 | E44: =IF($C$6="interino",-E56*4.82%,IF($C$9="si",2*AF102,AF102)) -> -51.68 | F44: =IF($C$6="interino",-F56*4.82%,IF($C$9="si",2*AG102,AG102)) -> -51.68 | G44: =IF($C$6="interino",-G56*4.82%,IF($C$9="si",2*AC102,AC102)) -> -51.68 | H44: =IF($C$6="interino",-H56*4.82%,IF($C$9="si",2*AH102,AH102)) -> -51.68 | I44: =IF($C$6="interino",-I56*4.82%,IF($C$9="si",2*AI102,AI102)) -> -51.68 | J44: =IF($C$6="interino",-J56*4.82%,IF($C$9="si",2*AJ102,AJ102)) -> -51.68 | K44: =IF($C$6="interino",-K56*4.82%,IF($C$9="si",2*AK102,AK102)) -> -51.68 | L44: =IF($C$6="interino",-L56*4.82%,IF($C$9="si",2*AL102,AL102)) -> -51.68 | M44: =IF($C$6="interino",-M56*4.82%,IF($C$9="si",2*AM102,AM102)) -> -51.68 | N44: =IF($C$6="interino",-N56*4.82%,IF($C$9="si",2*AN102,AN102)) -> -51.68 | O44: =IF($C$6="interino",-O56*4.82%,IF($C$9="si",2*AO102,AO102)) -> -51.68 | ... T44: =IF($C$6="interino",-T56*4.82%,IF($C$9="si",2*AT102,AT102)) -> -51.68
B45: =IF(C6=AA72,"Derechos Pasivos","Cuota Desempleo") -> Derechos Pasivos | C45: =IF($C$6="interino",-C56*1.55%,IF($C$9="si",-2*AD103,-AD103)) -> -118.04 | D45: =IF($C$6="interino",-D56*1.55%,IF($C$9="si",-2*AE103,-AE103)) -> -118.04 | E45: =IF($C$6="interino",-E56*1.55%,IF($C$9="si",-2*AF103,-AF103)) -> -118.04 | F45: =IF($C$6="interino",-F56*1.55%,IF($C$9="si",-2*AG103,-AG103)) -> -118.04 | G45: =IF($C$6="interino",-G56*1.55%,IF($C$9="si",-2*AC103,-AC103)) -> -118.04 | H45: =IF($C$6="interino",-H56*1.55%,IF($C$9="si",-2*AH103,-AH103)) -> -118.04 | I45: =IF($C$6="interino",-I56*1.55%,IF($C$9="si",-2*AI103,-AI103)) -> -118.04 | J45: =IF($C$6="interino",-J56*1.55%,IF($C$9="si",-2*AJ103,-AJ103)) -> -118.04 | K45: =IF($C$6="interino",-K56*1.55%,IF($C$9="si",-2*AK103,-AK103)) -> -118.04 | L45: =IF($C$6="interino",-L56*1.55%,IF($C$9="si",-2*AL103,-AL103)) -> -118.04 | M45: =IF($C$6="interino",-M56*1.55%,IF($C$9="si",-2*AM103,-AM103)) -> -118.04 | N45: =IF($C$6="interino",-N56*1.55%,IF($C$9="si",-2*AN103,-AN103)) -> -118.04 | O45: =IF($C$6="interino",-O56*1.55%,IF($C$9="si",-2*AO103,-AO103)) -> -118.04 | ... T45: =IF($C$6="interino",-T56*1.55%,IF($C$9="si",-2*AT103,-AT103)) -> -118.04
B46: =IF(C6=AA72," ","Cuota Formación Profesional") | C46: =IF($C$6="interino",-C56*0.1%," ") | D46: =IF($C$6="interino",-D56*0.1%," ") | E46: =IF($C$6="interino",-E56*0.1%," ") | F46: =IF($C$6="interino",-F56*0.1%," ") | G46: =IF($C$6="interino",-G56*0.1%," ") | H46: =IF($C$6="interino",-H56*0.1%," ") | I46: =IF($C$6="interino",-I56*0.1%," ") | J46: =IF($C$6="interino",-J56*0.1%," ") | ... T46: =IF($C$6="interino",-T56*0.1%," ")
B47: Cuota Sindical
B48: % Retención IRPF | C48: =-C41*$C$14 -> -824.184 | D48: =-D41*$C$14 -> -782.148 | E48: =-E41*$C$14 -> -719.8536 | F48: =-F41*$C$14 -> -904.6392 | G48: =-G41*$C$14 -> -896.2368 | H48: =-H41*$C$14 -> -846.9696 | I48: =-I41*$C$14 -> -729.0576 | J48: =-J41*$C$14 -> -699.792 | ... T48: =-T41*$C$14 -> -729.3912
B49: TOTAL DE GASTOS | C49: =SUM(C44:C48) -> -993.904 | D49: =SUM(D44:D48) -> -951.868 | E49: =SUM(E44:E48) -> -889.5736 | F49: =SUM(F44:F48) -> -1074.3592 | G49: =SUM(G44:G48) -> -1065.9568 | H49: =SUM(H44:H48) -> -1016.6896 | I49: =SUM(I44:I48) -> -898.7776 | J49: =SUM(J44:J48) -> -869.512 | ... T49: =SUM(T44:T48) -> -899.1112
U50: SUELDO BRUTO MEDIO ANUAL
B51: SUELDO MENSUAL LIQUIDO A PERCIBIR | C51: =+C41+C49 -> 2440.196 | D51: =+D41+D49 -> 2307.082 | E51: =+E41+E49 -> 2109.8164 | F51: =+F41+F49 -> 2694.9708 | G51: =+G41+G49 -> 2668.3632 | H51: =+H41+H49 -> 2512.3504 | I51: =+I41+I49 -> 2138.9624 | J51: =+J41+J49 -> 2046.288 | ... T51: =+T41+T49 -> 2140.0188
B53: SUELDO BRUTO ANUAL | C53: =+AD104 -> 46526.58 | D53: =+AE104 -> 44370.816 | E53: =+AF104 -> 43975.82 | F53: =+AG104 -> 49767.28 | G53: =+AC104 -> 50376.4 | H53: =+AH104 -> 48303.32 | I53: =+AI104 -> 41425.12 | J53: =+AJ104 -> 39663.88 | K53: =+AK104 -> 39365.16 | L53: =+AL104 -> 42106.92 | M53: =+AM104 -> 45288.64 | N53: =+AN104 -> 42008.5 | O53: =+AO104 -> 48798.948 | ... T53: =+AT104 -> 47291.16 | U53: =SUM(C53:T53)/18 -> 45406.179
B54: =IF(C6="carrera","Cuantía desgravable en la Declaración de la Renta: Derechos Pasivos, MUFACE y cuota sindical","Cuantía desgravable en a Declaración de la Renta: Seguridad Social y cuota sindical") -> Cuantía desgravable en la Declaración de la Renta: Derechos Pasivos, MUFACE y cuota sindical | C54: =IF($C6="carrera",(+(AD102+AD103)*14)+(C47*12),-(C53*6.35%)-(C47*12)) -> 929.04 | D54: =IF($C6="carrera",(+(AE102+AE103)*14)+(D47*12),-(D53*6.35%)-(D47*12)) -> 929.04 | E54: =IF($C6="carrera",(+(AF102+AF103)*14)+(E47*12),-(E53*6.35%)-(E47*12)) -> 929.04 | F54: =IF($C6="carrera",(+(AG102+AG103)*14)+(F47*12),-(F53*6.35%)-(F47*12)) -> 929.04 | G54: =IF($C6="carrera",(+(AC102+AC103)*14)+(G47*12),-(G53*6.35%)-(G47*12)) -> 929.04 | H54: =IF($C6="carrera",(+(AH102+AH103)*14)+(H47*12),-(H53*6.35%)-(H47*12)) -> 929.04 | I54: =IF($C6="carrera",(+(AI102+AI103)*14)+(I47*12),-(I53*6.35%)-(I47*12)) -> 929.04 | J54: =IF($C6="carrera",(+(AJ102+AJ103)*14)+(J47*12),-(J53*6.35%)-(J47*12)) -> 929.04 | K54: =IF($C6="carrera",(+(AK102+AK103)*14)+(K47*12),-(K53*6.35%)-(K47*12)) -> 929.04 | L54: =IF($C6="carrera",(+(AL102+AL103)*14)+(L47*12),-(L53*6.35%)-(L47*12)) -> 929.04 | M54: =IF($C6="carrera",(+(AM102+AM103)*14)+(M47*12),-(M53*6.35%)-(M47*12)) -> 929.04 | N54: =IF($C6="carrera",(+(AN102+AN103)*14)+(N47*12),-(N53*6.35%)-(N47*12)) -> 929.04 | O54: =IF($C6="carrera",(+(AO102+AO103)*14)+(O47*12),-(O53*6.35%)-(O47*12)) -> 929.04 | ... T54: =IF($C6="carrera",(+(AT102+AT103)*14)+(T47*12),-(T53*6.35%)-(T47*12)) -> 929.04
B56: =IF(C6="interino","Base cotización Seguridad Social"," ") | C56: =IF($C$6="interino",+C53/12," ") | D56: =IF($C$6="interino",+D53/12," ") | E56: =IF($C$6="interino",+E53/12," ") | F56: =IF($C$6="interino",+F53/12," ") | G56: =IF($C$6="interino",+G53/12," ") | H56: =IF($C$6="interino",+H53/12," ") | I56: =IF($C$6="interino",+I53/12," ") | J56: =IF($C$6="interino",+J53/12," ") | ... T56: =IF($C$6="interino",+T53/12," ")
B58: COMPARATIVA DE RETRIBUCIONES POR COMUNIDADES
B59: Selecciona la Comunidad: | C59: Andalucía | D59: Aragón | E59: Asturias | F59: Baleares (Islas) | G59: Canarias | H59: Cantabria | I59: Castilla La Mancha | J59: Castilla y León | K59: Cataluña | L59: Extremadura | M59: Galicia | N59: La Rioja | O59: Madrid | P59: Murcia | Q59: Valencia | R59: Ceuta y Melilla | S59: País Vasco | T59: Navarra
B60: Castilla y León | C60: =IF(C61>0,"Al año cobra más:","Al año cobra menos:") -> Al año cobra más: | D60: =IF(D61>0,"Al año cobra más:","Al año cobra menos:") -> Al año cobra más: | E60: =IF(E61>0,"Al año cobra más:","Al año cobra menos:") -> Al año cobra más: | F60: =IF(F61>0,"Al año cobra más:","Al año cobra menos:") -> Al año cobra más: | G60: =IF(G61>0,"Al año cobra más:","Al año cobra menos:") -> Al año cobra más: | H60: =IF(H61>0,"Al año cobra más:","Al año cobra menos:") -> Al año cobra más: | I60: =IF(I61>0,"Al año cobra más:","Al año cobra menos:") -> Al año cobra más: | J60: =IF(J61>0,"Al año cobra más:","Al año cobra menos:") -> Al año cobra menos: | ... T60: =IF(T61>0,"Al año cobra más:","Al año cobra menos:") -> Al año cobra más:
C61: =IF($B$60=$C$59,C53-$C$53,IF($B$60=$D$59,C53-$D$53,IF($B$60=$E$59,C53-$E$53,IF($B$60=$F$59,C53-$F$53,IF($B$60=$G$59,C53-$G$53,IF($B$60=$H$59,C53-$H$53,IF($B$60=$I$59,C53-$I$53,IF($B$60=$J$59,C53-$J$53,IF($B$60=$K$59,C53-$K$53,IF($B$60=$L$59,C53-$L$53,IF($B$60=$M$59,C53-$M$53,IF($B$60=$N$59,C53-$N$53,IF($B$60=$O$59,C53-$O$53,IF($B$60=$P$59,C53-$P$53,IF($B$60=$Q$59,C53-$Q$53,IF($B$60=$R$59,C53-$R$53,IF($B$60=$S$59,C53-$S$53,IF($B$60=$T$59,C53-$T$53)))))))))))))))))) -> 6862.7 | D61: =IF($B$60=$C$59,D53-$C$53,IF($B$60=$D$59,D53-$D$53,IF($B$60=$E$59,D53-$E$53,IF($B$60=$F$59,D53-$F$53,IF($B$60=$G$59,D53-$G$53,IF($B$60=$H$59,D53-$H$53,IF($B$60=$I$59,D53-$I$53,IF($B$60=$J$59,D53-$J$53,IF($B$60=$K$59,D53-$K$53,IF($B$60=$L$59,D53-$L$53,IF($B$60=$M$59,D53-$M$53,IF($B$60=$N$59,D53-$N$53,IF($B$60=$O$59,D53-$O$53,IF($B$60=$P$59,D53-$P$53,IF($B$60=$Q$59,D53-$Q$53,IF($B$60=$R$59,D53-$R$53,IF($B$60=$S$59,D53-$S$53,IF($B$60=$T$59,D53-$T$53)))))))))))))))))) -> 4706.936 | E61: =IF($B$60=$C$59,E53-$C$53,IF($B$60=$D$59,E53-$D$53,IF($B$60=$E$59,E53-$E$53,IF($B$60=$F$59,E53-$F$53,IF($B$60=$G$59,E53-$G$53,IF($B$60=$H$59,E53-$H$53,IF($B$60=$I$59,E53-$I$53,IF($B$60=$J$59,E53-$J$53,IF($B$60=$K$59,E53-$K$53,IF($B$60=$L$59,E53-$L$53,IF($B$60=$M$59,E53-$M$53,IF($B$60=$N$59,E53-$N$53,IF($B$60=$O$59,E53-$O$53,IF($B$60=$P$59,E53-$P$53,IF($B$60=$Q$59,E53-$Q$53,IF($B$60=$R$59,E53-$R$53,IF($B$60=$S$59,E53-$S$53,IF($B$60=$T$59,E53-$T$53)))))))))))))))))) -> 4311.94 | F61: =IF($B$60=$C$59,F53-$C$53,IF($B$60=$D$59,F53-$D$53,IF($B$60=$E$59,F53-$E$53,IF($B$60=$F$59,F53-$F$53,IF($B$60=$G$59,F53-$G$53,IF($B$60=$H$59,F53-$H$53,IF($B$60=$I$59,F53-$I$53,IF($B$60=$J$59,F53-$J$53,IF($B$60=$K$59,F53-$K$53,IF($B$60=$L$59,F53-$L$53,IF($B$60=$M$59,F53-$M$53,IF($B$60=$N$59,F53-$N$53,IF($B$60=$O$59,F53-$O$53,IF($B$60=$P$59,F53-$P$53,IF($B$60=$Q$59,F53-$Q$53,IF($B$60=$R$59,F53-$R$53,IF($B$60=$S$59,F53-$S$53,IF($B$60=$T$59,F53-$T$53)))))))))))))))))) -> 10103.4 | G61: =IF($B$60=$C$59,G53-$C$53,IF($B$60=$D$59,G53-$D$53,IF($B$60=$E$59,G53-$E$53,IF($B$60=$F$59,G53-$F$53,IF($B$60=$G$59,G53-$G$53,IF($B$60=$H$59,G53-$H$53,IF($B$60=$I$59,G53-$I$53,IF($B$60=$J$59,G53-$J$53,IF($B$60=$K$59,G53-$K$53,IF($B$60=$L$59,G53-$L$53,IF($B$60=$M$59,G53-$M$53,IF($B$60=$N$59,G53-$N$53,IF($B$60=$O$59,G53-$O$53,IF($B$60=$P$59,G53-$P$53,IF($B$60=$Q$59,G53-$Q$53,IF($B$60=$R$59,G53-$R$53,IF($B$60=$S$59,G53-$S$53,IF($B$60=$T$59,G53-$T$53)))))))))))))))))) -> 10712.52 | H61: =IF($B$60=$C$59,H53-$C$53,IF($B$60=$D$59,H53-$D$53,IF($B$60=$E$59,H53-$E$53,IF($B$60=$F$59,H53-$F$53,IF($B$60=$G$59,H53-$G$53,IF($B$60=$H$59,H53-$H$53,IF($B$60=$I$59,H53-$I$53,IF($B$60=$J$59,H53-$J$53,IF($B$60=$K$59,H53-$K$53,IF($B$60=$L$59,H53-$L$53,IF($B$60=$M$59,H53-$M$53,IF($B$60=$N$59,H53-$N$53,IF($B$60=$O$59,H53-$O$53,IF($B$60=$P$59,H53-$P$53,IF($B$60=$Q$59,H53-$Q$53,IF($B$60=$R$59,H53-$R$53,IF($B$60=$S$59,H53-$S$53,IF($B$60=$T$59,H53-$T$53)))))))))))))))))) -> 8639.44 | I61: =IF($B$60=$C$59,I53-$C$53,IF($B$60=$D$59,I53-$D$53,IF($B$60=$E$59,I53-$E$53,IF($B$60=$F$59,I53-$F$53,IF($B$60=$G$59,I53-$G$53,IF($B$60=$H$59,I53-$H$53,IF($B$60=$I$59,I53-$I$53,IF($B$60=$J$59,I53-$J$53,IF($B$60=$K$59,I53-$K$53,IF($B$60=$L$59,I53-$L$53,IF($B$60=$M$59,I53-$M$53,IF($B$60=$N$59,I53-$N$53,IF($B$60=$O$59,I53-$O$53,IF($B$60=$P$59,I53-$P$53,IF($B$60=$Q$59,I53-$Q$53,IF($B$60=$R$59,I53-$R$53,IF($B$60=$S$59,I53-$S$53,IF($B$60=$T$59,I53-$T$53)))))))))))))))))) -> 1761.24 | J61: =IF($B$60=$C$59,J53-$C$53,IF($B$60=$D$59,J53-$D$53,IF($B$60=$E$59,J53-$E$53,IF($B$60=$F$59,J53-$F$53,IF($B$60=$G$59,J53-$G$53,IF($B$60=$H$59,J53-$H$53,IF($B$60=$I$59,J53-$I$53,IF($B$60=$J$59,J53-$J$53,IF($B$60=$K$59,J53-$K$53,IF($B$60=$L$59,J53-$L$53,IF($B$60=$M$59,J53-$M$53,IF($B$60=$N$59,J53-$N$53,IF($B$60=$O$59,J53-$O$53,IF($B$60=$P$59,J53-$P$53,IF($B$60=$Q$59,J53-$Q$53,IF($B$60=$R$59,J53-$R$53,IF($B$60=$S$59,J53-$S$53,IF($B$60=$T$59,J53-$T$53)))))))))))))))))) -> 0 | ... T61: =IF($B$60=$C$59,T53-$C$53,IF($B$60=$D$59,T53-$D$53,IF($B$60=$E$59,T53-$E$53,IF($B$60=$F$59,T53-$F$53,IF($B$60=$G$59,T53-$G$53,IF($B$60=$H$59,T53-$H$53,IF($B$60=$I$59,T53-$I$53,IF($B$60=$J$59,T53-$J$53,IF($B$60=$K$59,T53-$K$53,IF($B$60=$L$59,T53-$L$53,IF($B$60=$M$59,T53-$M$53,IF($B$60=$N$59,T53-$N$53,IF($B$60=$O$59,T53-$O$53,IF($B$60=$P$59,T53-$P$53,IF($B$60=$Q$59,T53-$Q$53,IF($B$60=$R$59,T53-$R$53,IF($B$60=$S$59,T53-$S$53,IF($B$60=$T$59,T53-$T$53)))))))))))))))))) -> 7627.28
B63: COMPARATIVA DE RETRIBUCIONES POR COMUNIDADES CON RESPECTO A LA MEDIA
B64: Comunidad: | C64: Andalucía | D64: Aragón | E64: Asturias | F64: Baleares (Islas) | G64: Canarias | H64: Cantabria | I64: Castilla La Mancha | J64: Castilla y León | K64: Cataluña | L64: Extremadura | M64: Galicia | N64: La Rioja | O64: Madrid | P64: Murcia | Q64: Valencia | R64: Ceuta y Melilla | S64: País Vasco | T64: Navarra | U64: RETRIBUCIÓN MÁXIMA | V64: RETRIBUCIÓN MÍNIMA
B65: Diferencia absoluta | C65: =SUM(C53,-$U53) -> 1120.4009 | D65: =SUM(D53,-$U53) -> -1035.3631 | E65: =SUM(E53,-$U53) -> -1430.3591 | F65: =SUM(F53,-$U53) -> 4361.1009 | G65: =SUM(G53,-$U53) -> 4970.2209 | H65: =SUM(H53,-$U53) -> 2897.1409 | I65: =SUM(I53,-$U53) -> -3981.0591 | J65: =SUM(J53,-$U53) -> -5742.2991 | ... T65: =SUM(T53,-$U53) -> 1884.9809 | W65: BRECHA ANUAL
B66: Diferencia relativa | C66: =C65/$U53 -> 0.024675075 | D66: =D65/$U53 -> -0.022802251 | E66: =E65/$U53 -> -0.03150142 | F66: =F65/$U53 -> 0.096046419 | G66: =G65/$U53 -> 0.10946133 | H66: =H65/$U53 -> 0.063804992 | I66: =I65/$U53 -> -0.087676594 | J66: =J65/$U53 -> -0.12646515 | ... T66: =T65/$U53 -> 0.041513753
B67: Elaborado por Manuel Pérez García. Secretario de Acción Sindical de ANPE ANDALUCÍA | U67: =MAX(C53:T53) -> 52344.14 | V67: =MIN(C53:T53) -> 39365.16 | W67: =U67-V67 -> 12978.98
U68: =INDEX($C$59:$T$59,MATCH(MAX($C$53:$T$53),$C$53:$T$53,0)) -> Ceuta y Melilla | V68: =INDEX($C$59:$T$59,MATCH(MIN($C$53:$T$53),$C$53:$T$53,0)) -> Cataluña
Y71: SI | Z71: 0
Y72: NO | Z72: 1 | AA72: Carrera
Z73: 2 | AA73: Interino
Z74: 3
Y75: 0.02 | Z75: 4 | AH75: 185 | AI75: =+AH75+35 -> 220 | AJ75: =+AI75+35 -> 255 | AK75: =+AJ75+35 -> 290 | AL75: =+AK75+35 -> 325 | AM75: =+AL75+35 -> 360 | AN75: =+AM75+35 -> 395 | AO75: =+AN75+35 -> 430 | AP75: =+AO75+35 -> 465 | ... AT75: =+AS75+35 -> 605
Y76: 0.03 | Z76: 5 | AA76: Canarias | AC76: =+Retribuciones!C10 -> Canarias | AD76: =+Retribuciones!C50 -> Andalucía | AE76: =+Retribuciones!C86 -> Aragón | AF76: =+Retribuciones!C122 -> Asturias | AG76: =+Retribuciones!C158 -> Baleares | AH76: =+Retribuciones!C194 -> Cantabria | AI76: =+Retribuciones!C230 -> Castilla La Mancha | AJ76: =+Retribuciones!C266 -> Castilla y León | AK76: =+Retribuciones!C302 -> Cataluña | AL76: =+Retribuciones!C338 -> Extremadura | AM76: =+Retribuciones!C374 -> Galicia | AN76: =+Retribuciones!C410 -> La Rioja | AO76: =+Retribuciones!C446 -> Madrid | AP76: =+Retribuciones!C482 -> Murcia | AQ76: =+Retribuciones!C518 -> Valencia | AR76: =+Retribuciones!C554 -> Ceuta y Melilla | AS76: =+Retribuciones!C590 -> País Vasco | AT76: =+Retribuciones!C626 -> Navarra
Y77: 0.04 | Z77: 6 | AA77: Andalucía | AC77: =+Retribuciones!C11 -> 590-Profesores Enseñanza Secundaria | AD77: =+Retribuciones!C51 -> 590-Profesores Enseñanza Secundaria | AE77: =+Retribuciones!C87 -> 590-Profesores Enseñanza Secundaria | AF77: =+Retribuciones!C123 -> 590-Profesores Enseñanza Secundaria | AG77: =+Retribuciones!C159 -> 590-Profesores Enseñanza Secundaria | AH77: =+Retribuciones!C195 -> 590-Profesores Enseñanza Secundaria | AI77: =+Retribuciones!C231 -> 590-Profesores Enseñanza Secundaria | AJ77: =+Retribuciones!C267 -> 590-Profesores Enseñanza Secundaria | AK77: =+Retribuciones!C303 -> 590-Profesores Enseñanza Secundaria | AL77: =+Retribuciones!C339 -> 590-Profesores Enseñanza Secundaria | AM77: =+Retribuciones!C375 -> 590-Profesores Enseñanza Secundaria | AN77: =+Retribuciones!C411 -> 590-Profesores Enseñanza Secundaria | AO77: =+Retribuciones!C447 -> 590-Profesores Enseñanza Secundaria | AP77: =+Retribuciones!C483 -> 590-Profesores Enseñanza Secundaria | AQ77: =+Retribuciones!C519 -> 590-Profesores Enseñanza Secundaria | AR77: =+Retribuciones!C555 -> 590-Profesores Enseñanza Secundaria | AS77: =+Retribuciones!C591 -> 590-Profesores Enseñanza Secundaria | AT77: =+Retribuciones!C627 -> 590-Profesores Enseñanza Secundaria
Y78: 0.05 | Z78: 7 | AA78: Aragón | AB78: Grupo | AC78: =+Retribuciones!C12 -> A1 | AD78: =+Retribuciones!C52 -> A1 | AE78: =+Retribuciones!C88 -> A1 | AF78: =+Retribuciones!C124 -> A1 | AG78: =+Retribuciones!C160 -> A1 | AH78: =+Retribuciones!C196 -> A1 | AI78: =+Retribuciones!C232 -> A1 | AJ78: =+Retribuciones!C268 -> A1 | AK78: =+Retribuciones!C304 -> A1 | AL78: =+Retribuciones!C340 -> A1 | AM78: =+Retribuciones!C376 -> A1 | AN78: =+Retribuciones!C412 -> A1 | AO78: =+Retribuciones!C448 -> A1 | AP78: =+Retribuciones!C484 -> A1 | AQ78: =+Retribuciones!C520 -> A1 | AR78: =+Retribuciones!C556 -> A1 | AS78: =+Retribuciones!C592 -> A1 | AT78: =+Retribuciones!C628 -> A1
Y79: 0.06 | Z79: 8 | AA79: Asturias | AC79: =+Retribuciones!C13 -> 24 | AD79: =+Retribuciones!C53 -> 24 | AE79: =+Retribuciones!C89 -> 24 | AF79: =+Retribuciones!C125 -> 24 | AG79: =+Retribuciones!C161 -> 24 | AH79: =+Retribuciones!C197 -> 24 | AI79: =+Retribuciones!C233 -> 24 | AJ79: =+Retribuciones!C269 -> 24 | AK79: =+Retribuciones!C305 -> 24 | AL79: =+Retribuciones!C341 -> 24 | AM79: =+Retribuciones!C377 -> 24 | AN79: =+Retribuciones!C413 -> 24 | AO79: =+Retribuciones!C449 -> 24 | AP79: =+Retribuciones!C485 -> 24 | AQ79: =+Retribuciones!C521 -> 24 | AR79: =+Retribuciones!C557 -> 24 | AS79: =+Retribuciones!C593 -> 24 | AT79: =+Retribuciones!C629 -> 24
Y80: 0.07 | Z80: 9 | AA80: Baleares (Islas) | AB80: Sueldo Base | AC80: =+Retribuciones!C14 -> 1387.24 | AD80: =+Retribuciones!C54 -> 1387.24 | AE80: =+Retribuciones!C90 -> 1387.24 | AF80: =+Retribuciones!C126 -> 1387.24 | AG80: =+Retribuciones!C162 -> 1387.24 | AH80: =+Retribuciones!C198 -> 1387.24 | AI80: =+Retribuciones!C234 -> 1387.24 | AJ80: =+Retribuciones!C270 -> 1387.24 | AK80: =+Retribuciones!C306 -> 1387.24 | AL80: =+Retribuciones!C342 -> 1387.24 | AM80: =+Retribuciones!C378 -> 1387.24 | AN80: =+Retribuciones!C414 -> 1387.24 | AO80: =+Retribuciones!C450 -> 1387.24 | AP80: =+Retribuciones!C486 -> 1387.24 | AQ80: =+Retribuciones!C522 -> 1387.24 | AR80: =+Retribuciones!C558 -> 1387.24 | AS80: =+Retribuciones!C594 -> 1387.24 | AT80: =+Retribuciones!C630 -> 2258.75
Y81: 0.08 | Z81: 10 | AA81: Cantabria | AB81: Extra Sueldo Base | AC81: =+Retribuciones!C15 -> 856.05 | AD81: =+Retribuciones!C55 -> 856.05 | AE81: =+Retribuciones!C91 -> 856.05 | AF81: =+Retribuciones!C127 -> 856.05 | AG81: =+Retribuciones!C163 -> 856.05 | AH81: =+Retribuciones!C199 -> 856.05 | AI81: =+Retribuciones!C235 -> 856.05 | AJ81: =+Retribuciones!C271 -> 856.05 | AK81: =+Retribuciones!C307 -> 856.05 | AL81: =+Retribuciones!C343 -> 856.05 | AM81: =+Retribuciones!C379 -> 856.05 | AN81: =+Retribuciones!C415 -> 856.05 | AO81: =+Retribuciones!C451 -> 856.05 | AP81: =+Retribuciones!C487 -> 856.05 | AQ81: =+Retribuciones!C523 -> 856.05 | AR81: =+Retribuciones!C559 -> 856.05 | AS81: =+Retribuciones!C595 -> 856.05 | AT81: =+Retribuciones!C631 -> 2258.75
Y82: 0.09 | Z82: 11 | AA82: Castilla y León | AB82: Trienios | AC82: =+Retribuciones!C16 -> 53.39 | AD82: =+Retribuciones!C56 -> 53.39 | AE82: =+Retribuciones!C92 -> 53.39 | AF82: =+Retribuciones!C128 -> 53.39 | AG82: =+Retribuciones!C164 -> 53.39 | AH82: =+Retribuciones!C200 -> 53.39 | AI82: =+Retribuciones!C236 -> 53.39 | AJ82: =+Retribuciones!C272 -> 53.39 | AK82: =+Retribuciones!C308 -> 53.39 | AL82: =+Retribuciones!C344 -> 53.39 | AM82: =+Retribuciones!C380 -> 53.39 | AN82: =+Retribuciones!C416 -> 53.39 | AO82: =+Retribuciones!C452 -> 53.39 | AP82: =+Retribuciones!C488 -> 53.39 | AQ82: =+Retribuciones!C524 -> 53.39 | AR82: =+Retribuciones!C560 -> 53.39 | AS82: =+Retribuciones!C596 -> 53.39 | AT82: =+Retribuciones!C632 -> 0
Y83: 0.1 | Z83: 12 | AA83: Castilla-La Mancha | AB83: Extra Trienio | AC83: =+Retribuciones!C17 -> 32.96 | AD83: =+Retribuciones!C57 -> 32.96 | AE83: =+Retribuciones!C93 -> 32.96 | AF83: =+Retribuciones!C129 -> 32.96 | AG83: =+Retribuciones!C165 -> 32.96 | AH83: =+Retribuciones!C201 -> 32.96 | AI83: =+Retribuciones!C237 -> 32.96 | AJ83: =+Retribuciones!C273 -> 32.96 | AK83: =+Retribuciones!C309 -> 32.96 | AL83: =+Retribuciones!C345 -> 32.96 | AM83: =+Retribuciones!C381 -> 32.96 | AN83: =+Retribuciones!C417 -> 32.96 | AO83: =+Retribuciones!C453 -> 32.96 | AP83: =+Retribuciones!C489 -> 32.96 | AQ83: =+Retribuciones!C525 -> 32.96 | AR83: =+Retribuciones!C561 -> 32.96 | AS83: =+Retribuciones!C597 -> 32.96 | AT83: =+Retribuciones!C633 -> 0
Y84: 0.11 | Z84: 13 | AA84: Cataluña | AB84: Complemento Destino | AC84: =+Retribuciones!C18 -> 728.32 | AD84: =+Retribuciones!C58 -> 729.14 | AE84: =+Retribuciones!C94 -> 729.14 | AF84: =+Retribuciones!C130 -> 736.54 | AG84: =+Retribuciones!C166 -> 718.36 | AH84: =+Retribuciones!C202 -> 767.49 | AI84: =+Retribuciones!C238 -> 729.14 | AJ84: =+Retribuciones!C274 -> 729.14 | AK84: =+Retribuciones!C310 -> 729.14 | AL84: =+Retribuciones!C346 -> 729.14 | AM84: =+Retribuciones!C382 -> 729.14 | AN84: =+Retribuciones!C418 -> 729.14 | AO84: =+Retribuciones!C454 -> 729.14 | AP84: =+Retribuciones!C490 -> 729.14 | AQ84: =+Retribuciones!C526 -> 729.14 | AR84: =+Retribuciones!C562 -> 729.14 | AS84: =+Retribuciones!C598 -> 817.32 | AT84: =+Retribuciones!C634 -> 0
Y85: 0.12 | Z85: 14 | AA85: Comunidad Valenciana | AB85: Complemento Específico | AC85: =+Retribuciones!C19 -> 757.35 | AD85: =+Retribuciones!C59 -> 881.46 | AE85: =+Retribuciones!C95 -> 756.22 | AF85: =+Retribuciones!C131 -> 708.37 | AG85: =+Retribuciones!C167 -> 450.98 | AH85: =+Retribuciones!C203 -> 875.1 | AI85: =+Retribuciones!C239 -> 282 | AJ85: =+Retribuciones!C275 -> 294.2 | AK85: =+Retribuciones!C311 -> 720.83 | AL85: =+Retribuciones!C347 -> 520.73 | AM85: =+Retribuciones!C383 -> 779.29 | AN85: =+Retribuciones!C419 -> 909.64 | AO85: =+Retribuciones!C455 -> 798.41 | AP85: =+Retribuciones!C491 -> 433.42 | AQ85: =+Retribuciones!C527 -> 731 | AR85: =+Retribuciones!C563 -> 433.91 | AS85: =+Retribuciones!C599 -> 1034.64 | AT85: =+Retribuciones!C635 -> 756.23
Y86: 0.13 | Z86: 15 | AA86: Extremadura | AB86: Extra Complemento Específico Autonómico | AC86: =+Retribuciones!C20 -> 590.73 | AD86: =+Retribuciones!C60 -> 0 | AE86: =+Retribuciones!C96 -> 680.598 | AF86: =+Retribuciones!C132 -> 0 | AG86: =IF($C$6="Carrera",+Retribuciones!C168,+Retribuciones!C169) -> 429.57 | AH86: =+Retribuciones!C204 -> 0 | AI86: =+Retribuciones!C240 -> 585.97 | AJ86: =+Retribuciones!C276 -> 424.79 | AK86: =+Retribuciones!C312 -> 0 | AL86: =+Retribuciones!C348 -> 181.99 | AM86: =+Retribuciones!C384 -> 0 | AN86: =+Retribuciones!C420 -> 0 | AO86: =+Retribuciones!C456 -> 0 | AP86: =+Retribuciones!C492 -> 444.36 | AQ86: =+Retribuciones!C528 -> 0 | AR86: =+Retribuciones!C564 -> 0 | AS86: =+Retribuciones!C600 -> 0 | AT86: =+Retribuciones!C636 -> 0
Y87: 0.14 | Z87: 16 | AA87: Galicia | AB87: Sin sexenio | AC87: =+Retribuciones!C21 -> 0 | AD87: =+Retribuciones!C61 -> 0 | AE87: =+Retribuciones!C97 -> 0 | AF87: =+Retribuciones!C133 -> 113.85 | AG87: 0 | AH87: =+Retribuciones!C205 -> 35.77 | AI87: =+Retribuciones!C241 -> 0 | AJ87: =+Retribuciones!C277 -> 0 | AK87: =+Retribuciones!C313 -> 0 | AL87: =+Retribuciones!C349 -> 0 | AM87: =+Retribuciones!C385 -> 0 | AN87: =+Retribuciones!C421 -> 0 | AO87: =+Retribuciones!C457 -> 0 | AP87: =+Retribuciones!C493 -> 0 | AQ87: =+Retribuciones!C529 -> 0 | AR87: =+Retribuciones!C565 -> 0 | AS87: =+Retribuciones!C601 -> 0 | AT87: =+Retribuciones!C638 -> 24.15
Y88: 0.15 | Z88: 17 | AA88: Madrid (Comunidad de) | AB88: 1º Sexenio | AC88: =+Retribuciones!C22 -> 55 | AD88: =+Retribuciones!C62 -> 85.62 | AE88: =+Retribuciones!C98 -> 96.53 | AF88: =+Retribuciones!C134 -> 120.17 | AG88: =+Retribuciones!C170 -> 68.45 | AH88: =+Retribuciones!C206 -> 108.86 | AI88: =+Retribuciones!C242 -> 90.35 | AJ88: =+Retribuciones!C278 -> 70.22 | AK88: =+Retribuciones!C314 -> 128.88 | AL88: =+Retribuciones!C350 -> 63.89 | AM88: =+Retribuciones!C386 -> 89.63 | AN88: =+Retribuciones!C422 -> 74.3 | AO88: =+Retribuciones!C458 -> 93.28 | AP88: =+Retribuciones!C494 -> 70.45 | AQ88: =+Retribuciones!C530 -> 126.47 | AR88: =+Retribuciones!C566 -> 69.49 | AS88: =+Retribuciones!C602 -> 89.91 | AT88: =+Retribuciones!C639 -> 227.44
Y89: 0.16 | Z89: 18 | AA89: Murcia (Región de) | AB89: 2º Sexenio | AC89: =+Retribuciones!C23 -> 64 | AD89: =+Retribuciones!C63 -> 99.51 | AE89: =+Retribuciones!C99 -> 114.53 | AF89: =+Retribuciones!C135 -> 88.42 | AG89: =+Retribuciones!C171 -> 86.34 | AH89: =+Retribuciones!C207 -> 92.21 | AI89: =+Retribuciones!C243 -> 84.89 | AJ89: =+Retribuciones!C279 -> 88.56 | AK89: =+Retribuciones!C315 -> 136.54 | AL89: =+Retribuciones!C351 -> 80.58 | AM89: =+Retribuciones!C387 -> 115.23 | AN89: =+Retribuciones!C423 -> 93.73 | AO89: =+Retribuciones!C459 -> 117.7 | AP89: =+Retribuciones!C495 -> 88.89 | AQ89: =+Retribuciones!C531 -> 133.97 | AR89: =+Retribuciones!C567 -> 87.67 | AS89: =+Retribuciones!C603 -> 0 | AT89: =+Retribuciones!C640 -> 251.59
Y90: 0.17 | Z90: 19 | AA90: Navarra (Comunidad Foral de) | AB90: 3º Sexenio | AC90: =+Retribuciones!C24 -> 120 | AD90: =+Retribuciones!C64 -> 127.77 | AE90: =+Retribuciones!C100 -> 143.73 | AF90: =+Retribuciones!C136 -> 117.87 | AG90: =+Retribuciones!C172 -> 115.06 | AH90: =+Retribuciones!C208 -> 122.88 | AI90: =+Retribuciones!C244 -> 113.11 | AJ90: =+Retribuciones!C280 -> 124.87 | AK90: =+Retribuciones!C316 -> 153.66 | AL90: =+Retribuciones!C352 -> 107.36 | AM90: =+Retribuciones!C388 -> 153.66 | AN90: =+Retribuciones!C424 -> 124.96 | AO90: =+Retribuciones!C460 -> 156.82 | AP90: =+Retribuciones!C496 -> 118.44 | AQ90: =+Retribuciones!C532 -> 153.24 | AR90: =+Retribuciones!C568 -> 116.79 | AS90: =+Retribuciones!C604 -> 0 | AT90: =+Retribuciones!C641 -> 454.88
Y91: 0.18 | Z91: 20 | AA91: País Vasco | AB91: 4º Sexenio | AC91: =+Retribuciones!C25 -> 180 | AD91: =+Retribuciones!C65 -> 162.29 | AE91: =+Retribuciones!C101 -> 162.77 | AF91: =+Retribuciones!C137 -> 161.35 | AG91: =+Retribuciones!C173 -> 157.41 | AH91: =+Retribuciones!C209 -> 168.17 | AI91: =+Retribuciones!C245 -> 154.79 | AJ91: =+Retribuciones!C281 -> 251.87 | AK91: =+Retribuciones!C317 -> 166.39 | AL91: =+Retribuciones!C353 -> 146.9 | AM91: =+Retribuciones!C389 -> 217.64 | AN91: =+Retribuciones!C425 -> 171 | AO91: =+Retribuciones!C461 -> 214.64 | AP91: =+Retribuciones!C497 -> 162.07 | AQ91: =+Retribuciones!C533 -> 166.8 | AR91: =+Retribuciones!C569 -> 159.78 | AS91: =+Retribuciones!C605 -> 53.63 | AT91: =+Retribuciones!C642 -> 472.99
Y92: 0.19 | Z92: 21 | AA92: Rioja (La) | AB92: 5º Sexenio | AC92: =+Retribuciones!C26 -> 70 | AD92: =+Retribuciones!C66 -> 63.4 | AE92: =+Retribuciones!C102 -> 60.09 | AF92: =+Retribuciones!C138 -> 47.46 | AG92: =+Retribuciones!C174 -> 46.36 | AH92: =+Retribuciones!C210 -> 49.51 | AI92: =+Retribuciones!C246 -> 59.41 | AJ92: =+Retribuciones!C282 -> 144.8 | AK92: =+Retribuciones!C318 -> 145.85 | AL92: =+Retribuciones!C354 -> 43.29 | AM92: =+Retribuciones!C390 -> 64 | AN92: =+Retribuciones!C426 -> 50.32 | AO92: =+Retribuciones!C462 -> 63.2 | AP92: =+Retribuciones!C498 -> 47.38 | AQ92: =+Retribuciones!C534 -> 96.97 | AR92: =+Retribuciones!C570 -> 47.08 | AS92: =+Retribuciones!C606 -> 44.44 | AT92: =+Retribuciones!C643 -> 676.28
Y93: 0.2 | Z93: 22 | AB93: Tutoría | AC93: =+Retribuciones!C27 -> 35 | AD93: =+Retribuciones!C67 -> 31.97 | AE93: =+Retribuciones!C103 -> 0 | AF93: =+Retribuciones!C139 -> 0 | AG93: =+Retribuciones!C175 -> 36.71 | AH93: =+Retribuciones!C211 -> 0 | AI93: =+Retribuciones!C247 -> 0 | AJ93: =+Retribuciones!C283 -> 0 | AK93: =+Retribuciones!C319 -> 93.6 | AL93: =+Retribuciones!C355 -> 47.72 | AM93: =+Retribuciones!C391 -> 66.04 | AN93: =+Retribuciones!C427 -> 0 | AO93: =+Retribuciones!C463 -> 70.94 | AP93: =+Retribuciones!C499 -> 0 | AQ93: =+Retribuciones!C535 -> 0 | AR93: =+Retribuciones!C571 -> 63.23 | AS93: =+Retribuciones!C607 -> 62.45 | AT93: =+Retribuciones!C644 -> 694.39
Y94: 0.21 | Z94: 23 | AB94: Residencia Isla Capitalina | AC94: =+Retribuciones!C29 -> 160.59 | AD94: =+Retribuciones!C69 -> 0 | AE94: =+Retribuciones!C105 -> 0 | AF94: =+Retribuciones!C141 -> 0 | AG94: =+Retribuciones!C177 -> 0 | AH94: =+Retribuciones!C213 -> 0 | AI94: =+Retribuciones!C249 -> 0 | AJ94: =+Retribuciones!C285 -> 0 | AK94: =+Retribuciones!C321 -> 0 | AL94: =+Retribuciones!C357 -> 0 | AM94: =+Retribuciones!C393 -> 0 | AN94: =+Retribuciones!C429 -> 0 | AO94: =+Retribuciones!C465 -> 0 | AP94: =+Retribuciones!C501 -> 0 | AQ94: =+Retribuciones!C537 -> 0 | AR94: =+Retribuciones!C573 -> 66.76 | AS94: =+Retribuciones!C609 -> 0 | AT94: =+Retribuciones!C645 -> 706.47
Y95: 0.22 | Z95: 24 | AA95: 510-Inspección | AB95: Residencia Isla No Capitalina | AC95: =+Retribuciones!C30 -> 534.9 | AD95: =+Retribuciones!C70 -> 0 | AE95: =+Retribuciones!C106 -> 0 | AF95: =+Retribuciones!C142 -> 0 | AG95: =+Retribuciones!C178 -> 693.08 | AH95: =+Retribuciones!C214 -> 0 | AI95: =+Retribuciones!C250 -> 0 | AJ95: =+Retribuciones!C286 -> 0 | AK95: =+Retribuciones!C322 -> 0 | AL95: =+Retribuciones!C358 -> 0 | AM95: =+Retribuciones!C394 -> 0 | AN95: =+Retribuciones!C430 -> 0 | AO95: =+Retribuciones!C466 -> 0 | AP95: =+Retribuciones!C502 -> 0 | AQ95: =+Retribuciones!C538 -> 0 | AR95: =+Retribuciones!C574 -> 1102.57 | AS95: =+Retribuciones!C610 -> 0 | AT95: =IF(Retribuciones!$C$11=Retribuciones!$F$11,Retribuciones!F651,IF(Retribuciones!$C$11=Retribuciones!$G$11,Retribuciones!G651,IF(Retribuciones!$C$11=Retribuciones!$H$11,Retribuciones!H651,IF(Retribuciones!$C$11=Retribuciones!$I$11,Retribuciones!I651,IF(Retribuciones!$C$11=Retribuciones!$J$11,Retribuciones!J651,IF(Retribuciones!$C$11=Retribuciones!$K$11,Retribuciones!K651,IF(Retribuciones!$C$11=Retribuciones!$L$11,Retribuciones!L651,IF(Retribuciones!$C$11=Retribuciones!$M$11,Retribuciones!M651,IF(Retribuciones!$C$11=Retribuciones!$N$11,Retribuciones!N651,0))))))))) -> 24.15 | AU95: ANTIGÜEDAD NAVARRA
Y96: 0.23 | Z96: 25 | AA96: 511-Catedráticos | AB96: Trienios Residencia Isla No Capitalina | AC96: =+Retribuciones!C31 -> 37.63 | AD96: =+Retribuciones!C71 -> 0 | AE96: =+Retribuciones!C107 -> 0 | AF96: =+Retribuciones!C143 -> 0 | AG96: =+Retribuciones!C179 -> 0 | AH96: =+Retribuciones!C215 -> 0 | AI96: =+Retribuciones!C251 -> 0 | AJ96: =+Retribuciones!C287 -> 0 | AK96: =+Retribuciones!C323 -> 0 | AL96: =+Retribuciones!C359 -> 0 | AM96: =+Retribuciones!C395 -> 0 | AN96: =+Retribuciones!C431 -> 0 | AO96: =+Retribuciones!C467 -> 0 | AP96: =+Retribuciones!C503 -> 0 | AQ96: =+Retribuciones!C539 -> 0 | AR96: =+Retribuciones!C575 -> 0 | AS96: =+Retribuciones!C611 -> 0 | AT96: =+Retribuciones!C647 -> 921.83
Y97: 0.24 | Z97: 26 | AA97: 590-Profesores Enseñanza Secundaria | AB97: Adicional maestros 1º y 2º ESO | AC97: =+Retribuciones!C32 -> 0 | AD97: =+Retribuciones!C72 -> 0 | AE97: =+Retribuciones!C108 -> 0 | AF97: =+Retribuciones!C144 -> 0 | AG97: =+Retribuciones!C180 -> 0 | AH97: =+Retribuciones!C216 -> 0 | AI97: =+Retribuciones!C252 -> 0 | AJ97: =+Retribuciones!C288 -> 0 | AK97: =+Retribuciones!C324 -> 0 | AL97: =+Retribuciones!C360 -> 0 | AM97: =+Retribuciones!C396 -> 0 | AN97: =+Retribuciones!C432 -> 0 | AO97: =+Retribuciones!C468 -> 0 | AP97: =+Retribuciones!C504 -> 0 | AQ97: =+Retribuciones!C540 -> 0 | AR97: =+Retribuciones!C576 -> 0 | AS97: =+Retribuciones!C612 -> 0 | AT97: =+Retribuciones!C652 -> 0
Y98: 0.25 | Z98: 27 | AA98: 591-Profesores Técnicos de Formación Profesional | AB98: Carrera profesional (evaluación docente) | AC98: =+Retribuciones!C33 -> 0 | AD98: =+Retribuciones!C73 -> 0 | AE98: =+Retribuciones!C109 -> 0 | AF98: =+Retribuciones!C145 -> 0 | AG98: =+Retribuciones!C181 -> 52.53 | AH98: =+Retribuciones!C217 -> 0 | AI98: =+Retribuciones!C253 -> 0 | AJ98: =+Retribuciones!C289 -> 27.04 | AK98: =+Retribuciones!C325 -> 0 | AL98: =+Retribuciones!C361 -> 0 | AM98: =+Retribuciones!C397 -> 0 | AN98: =+Retribuciones!C433 -> 0 | AO98: =+Retribuciones!C469 -> 0 | AP98: =+Retribuciones!C505 -> 160.6 | AQ98: =+Retribuciones!C541 -> 0 | AR98: =+Retribuciones!C577 -> 0 | AS98: =+Retribuciones!C613 -> 0 | AT98: =+Retribuciones!C649 -> 1149.27
Y99: 0.26 | Z99: 28 | AA99: 592-Profesores de Escuelas Oficiales de Idiomas | AB99: Productividad semestral (Murcia) | AC99: =+Retribuciones!C34 -> 0 | AD99: =+Retribuciones!C74 -> 0 | AE99: =+Retribuciones!C110 -> 0 | AF99: =+Retribuciones!C146 -> 0 | AG99: =+Retribuciones!C182 -> 80 | AH99: =+Retribuciones!C218 -> 0 | AI99: =+Retribuciones!C254 -> 0 | AJ99: =+Retribuciones!C290 -> 0 | AK99: =+Retribuciones!C326 -> 0 | AL99: =+Retribuciones!C362 -> 0 | AM99: =+Retribuciones!C398 -> 0 | AN99: =+Retribuciones!C434 -> 0 | AO99: =+Retribuciones!C470 -> 0 | AP99: =+Retribuciones!C506 -> 1080.9 | AQ99: =+Retribuciones!C542 -> 0 | AR99: =+Retribuciones!C578 -> 0 | AS99: =+Retribuciones!C614 -> 0 | AT99: =+Retribuciones!C650 -> 1149.27
Y100: 0.27 | Z100: 29 | AA100: 594-Profesores de Música y Artes Escénicas | AB100: Reducción 3% (Castilla la Mancha) | AC100: =+Retribuciones!C35 -> 0 | AD100: =+Retribuciones!C75 -> 0 | AE100: =+Retribuciones!C111 -> 0 | AF100: =+Retribuciones!C147 -> 0 | AG100: =+Retribuciones!C183 -> 0 | AH100: =+Retribuciones!C219 -> 0 | AI100: =+Retribuciones!C255 -> 0 | AJ100: =+Retribuciones!C291 -> 0 | AK100: =+Retribuciones!C327 -> 0 | AL100: =+Retribuciones!C363 -> 0 | AM100: =+Retribuciones!C399 -> 0 | AN100: =+Retribuciones!C435 -> 0 | AO100: =+Retribuciones!C471 -> 0 | AP100: =+Retribuciones!C507 -> 0 | AQ100: =+Retribuciones!C543 -> 0 | AR100: =+Retribuciones!C579 -> 0 | AS100: =+Retribuciones!C615 -> 0 | AT100: =+Retribuciones!C651 -> 24.15
Y101: 0.28 | Z101: 30 | AA101: 595-Profesores de Artes Plásticas y Diseño | AB101: Otros | AC101: =+Retribuciones!C36 -> 0 | AD101: =+Retribuciones!C76 -> 0 | AE101: =+Retribuciones!C112 -> 0 | AF101: =+Retribuciones!C148 -> 0 | AG101: =+Retribuciones!C184 -> 0 | AH101: =+Retribuciones!C220 -> 0 | AI101: =+Retribuciones!C256 -> 0 | AJ101: =+Retribuciones!C292 -> 0 | AK101: =+Retribuciones!C328 -> 0 | AL101: =+Retribuciones!C364 -> 0 | AM101: =+Retribuciones!C400 -> 0 | AN101: =+Retribuciones!C436 -> 0 | AO101: =+Retribuciones!C472 -> 0 | AP101: =+Retribuciones!C508 -> 0 | AQ101: =+Retribuciones!C544 -> 0 | AR101: =+Retribuciones!C580 -> 0 | AS101: =+Retribuciones!C616 -> 0 | AT101: =+Retribuciones!C652 -> 0
Y102: 0.29 | Z102: 31 | AA102: 596-Maestros de Taller de Artes Plásticas y Diseño | AB102: MUFACE | AC102: =+Retribuciones!C41 -> -51.68 | AD102: =+Retribuciones!C77 -> -51.68 | AE102: =+Retribuciones!C113 -> -51.68 | AF102: =+Retribuciones!C149 -> -51.68 | AG102: =+Retribuciones!C185 -> -51.68 | AH102: =+Retribuciones!C221 -> -51.68 | AI102: =+Retribuciones!C257 -> -51.68 | AJ102: =+Retribuciones!C293 -> -51.68 | AK102: =+Retribuciones!C329 -> -51.68 | AL102: =+Retribuciones!C365 -> -51.68 | AM102: =+Retribuciones!C401 -> -51.68 | AN102: =+Retribuciones!C437 -> -51.68 | AO102: =+Retribuciones!C473 -> -51.68 | AP102: =+Retribuciones!C509 -> -51.68 | AQ102: =+Retribuciones!C545 -> -51.68 | AR102: =+Retribuciones!C581 -> -51.68 | AS102: =+Retribuciones!C617 -> -51.68 | AT102: =+Retribuciones!C653 -> -51.68
Y103: 0.3 | Z103: 32 | AA103: 597-Maestros | AB103: Clases Pasivas | AC103: =+Retribuciones!C42 -> 118.04 | AD103: =+Retribuciones!C78 -> 118.04 | AE103: =+Retribuciones!C114 -> 118.04 | AF103: =+Retribuciones!C150 -> 118.04 | AG103: =+Retribuciones!C186 -> 118.04 | AH103: =+Retribuciones!C222 -> 118.04 | AI103: =+Retribuciones!C258 -> 118.04 | AJ103: =+Retribuciones!C294 -> 118.04 | AK103: =+Retribuciones!C330 -> 118.04 | AL103: =+Retribuciones!C366 -> 118.04 | AM103: =+Retribuciones!C402 -> 118.04 | AN103: =+Retribuciones!C438 -> 118.04 | AO103: =+Retribuciones!C474 -> 118.04 | AP103: =+Retribuciones!C510 -> 118.04 | AQ103: =+Retribuciones!C546 -> 118.04 | AR103: =+Retribuciones!C582 -> 118.04 | AS103: =+Retribuciones!C618 -> 118.04 | AT103: =+Retribuciones!C654 -> 118.04
Z104: 33 | AB104: SUELDO BRUTO ANUAL | AC104: =+Retribuciones!C43 -> 50376.4 | AD104: =+Retribuciones!C79 -> 46526.58 | AE104: =+Retribuciones!C115 -> 44370.816 | AF104: =+Retribuciones!C151 -> 43975.82 | AG104: =+Retribuciones!C187 -> 49767.28 | AH104: =+Retribuciones!C223 -> 48303.32 | AI104: =+Retribuciones!C259 -> 41425.12 | AJ104: =+Retribuciones!C295 -> 39663.88 | AK104: =+Retribuciones!C331 -> 39365.16 | AL104: =+Retribuciones!C367 -> 42106.92 | AM104: =+Retribuciones!C403 -> 45288.64 | AN104: =+Retribuciones!C439 -> 42008.5 | AO104: =+Retribuciones!C475 -> 48798.948 | AP104: =+Retribuciones!C511 -> 44422.12 | AQ104: =+Retribuciones!C547 -> 46283.4 | AR104: =+Retribuciones!C583 -> 52344.14 | AS104: =+Retribuciones!C619 -> 44993.02 | AT104: =+Retribuciones!C655 -> 47291.16
Z105: 34 | AA105: =+C5 -> 590-Profesores Enseñanza Secundaria | AC105: =+Retribuciones!C44 -> 0
Z106: 35
Z107: 36 | AB107: Andalucía
Z108: 37 | AB108: Aragón
Z109: 38 | AB109: Asturias
...

Sheet Retribuciones
B1: Cuerpo Docente | C1: =+'Nómina mensual'!C5:E5 -> 590-Profesores Enseñanza Secundaria | F1: Grupo prof: | G1: ='Nómina mensual'!H5 -> A1 | I1: Sin cargo
B2: Funcionario | C2: =+'Nómina mensual'!C6:E6 -> Carrera | E2: IMPORTANTE: PARA ACTUALIZAR CAMBIAR SÓLO LAS CELDAS SOMBREADAS | I2: Dirección | L2: A
B3: Años de Servicio a efectos de trienios | C3: =+'Nómina mensual'!C7:E7 -> 5 | I3: Vicedirección | L3: B
B4: Maestro de Primero y Segundo de la ESO | C4: =+'Nómina mensual'!C8:E8 -> NO | I4: Jefatura de Estudios | L4: C
B5: Nómina con Paga Extraordinaria | C5: =+'Nómina mensual'!C9:E9 -> NO | I5: Secretaría | L5: D
B6: Destino en Isla No Capitalina | C6: =+'Nómina mensual'!C10:E10 -> SI | L6: E
B7: Tutor | C7: =+'Nómina mensual'!C11:E11 -> SI | L7: F
B8: Cargo directivo | C8: ='Nómina mensual'!C12:D12 -> Vicedirección
C10: =+E11 -> Canarias
C11: =+C1 -> 590-Profesores Enseñanza Secundaria | E11: Canarias | F11: 597-Maestros | G11: 591-Profesores Técnicos de Formación Profesional | H11: 596-Maestros de Taller de Artes Plásticas y Diseño | I11: 590-Profesores Enseñanza Secundaria | J11: 592-Profesores de Escuelas Oficiales de Idiomas | K11: 594-Profesores de Música y Artes Escénicas | L11: 595-Profesores de Artes Plásticas y Diseño | M11: 511-Catedráticos | N11: 510-Inspección | O11: INSPECCION | P11: ACT. 02/26 | Q11: A2 | W11: A1
B12: Grupo | C12: =IF($C$11=$F$11,F12,IF($C$11=G$11,G12,IF($C$11=H$11,H12,IF($C$11=I$11,I12,IF($C$11=J$11,J12,IF($C$11=K$11,K12,IF($C$11=L$11,L12,IF($C$11=M$11,M12,N12)))))))) -> A1 | E12: Grupo | F12: A2 | G12: A2 | H12: A2 | I12: A1 | J12: A1 | K12: A1 | L12: A1 | M12: A1 | N12: A1 | R12: Sin cargo | S12: Dirección | T12: Vicedirección | U12: Jefatura de Estudios | V12: Secretaría | W12: Sin cargo | X12: Dirección | Y12: Vicedirección | Z12: Jefatura de Estudios | AA12: Secretaría
B13: =+E13 -> 24 | C13: =IF($C$11=$F$11,F13,IF($C$11=G$11,G13,IF($C$11=H$11,H13,IF($C$11=I$11,I13,IF($C$11=J$11,J13,IF($C$11=K$11,K13,IF($C$11=L$11,L13,IF($C$11=M$11,M13,N13)))))))) -> 24 | E13: =+H13 -> 24 | F13: 21 | G13: 24 | H13: 24 | I13: 24 | J13: 24 | K13: 24 | L13: 24 | M13: 26 | N13: 26 | Q13: A | R13: 0 | S13: 552.34 | T13: 226.64 | U13: =T13 -> 226.64 | V13: =U13 -> 226.64 | W13: 0 | X13: 694.22 | Y13: 341.27 | Z13: =Y13 -> 341.27 | AA13: =Z13 -> 341.27
B14: Sueldo Base | C14: =IF($C$11=$F$11,F14,IF($C$11=G$11,G14,IF($C$11=H$11,H14,IF($C$11=I$11,I14,IF($C$11=J$11,J14,IF($C$11=K$11,K14,IF($C$11=L$11,L14,IF($C$11=M$11,M14,N14)))))))) -> 1387.24 | E14: Sueldo Base | F14: =+F54 -> 1199.52 | G14: =+G54 -> 1199.52 | H14: =+H54 -> 1199.52 | I14: =+I54 -> 1387.24 | J14: =+J54 -> 1387.24 | K14: =+K54 -> 1387.24 | L14: =+L54 -> 1387.24 | M14: =+M54 -> 1387.24 | N14: =+N54 -> 1387.24 | Q14: B | R14: 0 | S14: 503.95 | T14: 217.21 | U14: =T14 -> 217.21 | V14: =U14 -> 217.21 | W14: 0 | X14: 617.53 | Y14: 327.09 | Z14: =Y14 -> 327.09 | AA14: =Z14 -> 327.09
B15: Extra Sueldo Base | C15: =IF($C$11=$F$11,F15,IF($C$11=G$11,G15,IF($C$11=H$11,H15,IF($C$11=I$11,I15,IF($C$11=J$11,J15,IF($C$11=K$11,K15,IF($C$11=L$11,L15,IF($C$11=M$11,M15,N15)))))))) -> 856.05 | E15: Extra Sueldo Base | F15: =+F55 -> 874.83 | G15: =+G55 -> 874.83 | H15: =+H55 -> 874.83 | I15: =+I55 -> 856.05 | J15: =+J55 -> 856.05 | K15: =+K55 -> 856.05 | L15: =+L55 -> 856.05 | M15: =+M55 -> 856.05 | N15: =+N55 -> 856.05 | Q15: C | R15: 0 | S15: 380.04 | T15: 203.02 | U15: =T15 -> 203.02 | V15: =U15 -> 203.02 | W15: 0 | X15: 556.11 | Y15: 253.88 | Z15: =Y15 -> 253.88 | AA15: =Z15 -> 253.88
B16: Trienios | C16: =IF($C$11=$F$11,F16,IF($C$11=G$11,G16,IF($C$11=H$11,H16,IF($C$11=I$11,I16,IF($C$11=J$11,J16,IF($C$11=K$11,K16,IF($C$11=L$11,L16,IF($C$11=M$11,M16,N16)))))))) -> 53.39 | E16: Trienios | F16: =+F56 -> 43.54 | G16: =+G56 -> 43.54 | H16: =+H56 -> 43.54 | I16: =+I56 -> 53.39 | J16: =+J56 -> 53.39 | K16: =+K56 -> 53.39 | L16: =+L56 -> 53.39 | M16: =+M56 -> 53.39 | N16: =+N56 -> 53.39 | Q16: D | R16: 0 | S16: 289.17 | U16: 158.18 | V16: =U16 -> 158.18 | W16: 0 | X16: 506.52 | Y16: 203.13 | Z16: =Y16 -> 203.13 | AA16: =Z16 -> 203.13
B17: Extra Trienio | C17: =IF($C$11=$F$11,F17,IF($C$11=G$11,G17,IF($C$11=H$11,H17,IF($C$11=I$11,I17,IF($C$11=J$11,J17,IF($C$11=K$11,K17,IF($C$11=L$11,L17,IF($C$11=M$11,M17,N17)))))))) -> 32.96 | E17: Extra Trienio | F17: =+F57 -> 31.74 | G17: =+G57 -> 31.74 | H17: =+H57 -> 31.74 | I17: =+I57 -> 32.96 | J17: =+J57 -> 32.96 | K17: =+K57 -> 32.96 | L17: =+L57 -> 32.96 | M17: =+M57 -> 32.96 | N17: =+N57 -> 32.96 | Q17: E | R17: 0 | S17: 195.96 | V17: 106.25 | W17: 0
B18: Complemento Destino | C18: =IF($C$11=$F$11,F18,IF($C$11=G$11,G18,IF($C$11=H$11,H18,IF($C$11=I$11,I18,IF($C$11=J$11,J18,IF($C$11=K$11,K18,IF($C$11=L$11,L18,IF($C$11=M$11,M18,N18)))))))) -> 728.32 | E18: Complemento Destino | F18: 591.43 | G18: 728.32 | H18: =+G18 -> 728.32 | I18: =+H18 -> 728.32 | J18: =+I18 -> 728.32 | K18: =+J18 -> 728.32 | L18: =+K18 -> 728.32 | M18: 872.33 | N18: =+M18 -> 872.33 | Q18: F | R18: 0 | S18: 122.79 | W18: 0
B19: Complemento Específico | C19: =IF($C$11=$F$11,F19,IF($C$11=G$11,G19,IF($C$11=H$11,H19,IF($C$11=I$11,I19,IF($C$11=J$11,J19,IF($C$11=K$11,K19,IF($C$11=L$11,L19,IF($C$11=M$11,M19,N19)))))))) -> 757.35 | E19: Complemento Específico | F19: 806.35 | G19: 759.63 | H19: =+G19 -> 759.63 | I19: 757.35 | J19: =+I19 -> 757.35 | K19: =+J19 -> 757.35 | L19: =+K19 -> 757.35 | M19: 816.85 | N19: 1515.22
B20: Extra Complemento Específico Autonómico | C20: =IF($C$11=$F$11,F20,IF($C$11=G$11,G20,IF($C$11=H$11,H20,IF($C$11=I$11,I20,IF($C$11=J$11,J20,IF($C$11=K$11,K20,IF($C$11=L$11,L20,IF($C$11=M$11,M20,N20)))))))) -> 590.73 | E20: Extra Complemento Específico | F20: 628.95 | G20: 592.51 | H20: =+G20 -> 592.51 | I20: 590.73 | J20: =+I20 -> 590.73 | K20: =+J20 -> 590.73 | L20: =+K20 -> 590.73 | M20: 637.15 | N20: =+M20 -> 637.15
B21: Sin sexenio | C21: =IF($C$11=$F$11,F21,IF($C$11=G$11,G21,IF($C$11=H$11,H21,IF($C$11=I$11,I21,IF($C$11=J$11,J21,IF($C$11=K$11,K21,IF($C$11=L$11,L21,IF($C$11=M$11,M21,N21)))))))) -> 0 | E21: Sin sexenio | Z21: SEXENIOS EXTRA
B22: 1º Sexenio | C22: =IF($C$11=$F$11,F22,IF($C$11=G$11,G22,IF($C$11=H$11,H22,IF($C$11=I$11,I22,IF($C$11=J$11,J22,IF($C$11=K$11,K22,IF($C$11=L$11,L22,IF($C$11=M$11,M22,N22)))))))) -> 55 | E22: 1º Sexenio | F22: 55 | G22: =+F22 -> 55 | H22: =+G22 -> 55 | I22: =+H22 -> 55 | J22: =+I22 -> 55 | K22: =+J22 -> 55 | L22: =+K22 -> 55 | M22: =+L22 -> 55 | N22: =+M22 -> 55 | Z22: 42.9 | AA22: =+Z22 -> 42.9 | AB22: =+AA22 -> 42.9 | AC22: =+AB22 -> 42.9 | AD22: =+AC22 -> 42.9 | AE22: =+AD22 -> 42.9 | AF22: =+AE22 -> 42.9 | AG22: =+AF22 -> 42.9 | AH22: =+AG22 -> 42.9
B23: 2º Sexenio | C23: =IF($C$11=$F$11,F23,IF($C$11=G$11,G23,IF($C$11=H$11,H23,IF($C$11=I$11,I23,IF($C$11=J$11,J23,IF($C$11=K$11,K23,IF($C$11=L$11,L23,IF($C$11=M$11,M23,N23)))))))) -> 64 | E23: 2º Sexenio | F23: 64 | G23: =+F23 -> 64 | H23: =+G23 -> 64 | I23: =+H23 -> 64 | J23: =+I23 -> 64 | K23: =+J23 -> 64 | L23: =+K23 -> 64 | M23: =+L23 -> 64 | N23: =+M23 -> 64 | Z23: 49.92 | AA23: =+Z23 -> 49.92 | AB23: =+AA23 -> 49.92 | AC23: =+AB23 -> 49.92 | AD23: =+AC23 -> 49.92 | AE23: =+AD23 -> 49.92 | AF23: =+AE23 -> 49.92 | AG23: =+AF23 -> 49.92 | AH23: =+AG23 -> 49.92
B24: 3º Sexenio | C24: =IF($C$11=$F$11,F24,IF($C$11=G$11,G24,IF($C$11=H$11,H24,IF($C$11=I$11,I24,IF($C$11=J$11,J24,IF($C$11=K$11,K24,IF($C$11=L$11,L24,IF($C$11=M$11,M24,N24)))))))) -> 120 | E24: 3º Sexenio | F24: 120 | G24: =+F24 -> 120 | H24: =+G24 -> 120 | I24: =+H24 -> 120 | J24: =+I24 -> 120 | K24: =+J24 -> 120 | L24: =+K24 -> 120 | M24: =+L24 -> 120 | N24: =+M24 -> 120 | Z24: 93.6 | AA24: =+Z24 -> 93.6 | AB24: =+AA24 -> 93.6 | AC24: =+AB24 -> 93.6 | AD24: =+AC24 -> 93.6 | AE24: =+AD24 -> 93.6 | AF24: =+AE24 -> 93.6 | AG24: =+AF24 -> 93.6 | AH24: =+AG24 -> 93.6
B25: 4º Sexenio | C25: =IF($C$11=$F$11,F25,IF($C$11=G$11,G25,IF($C$11=H$11,H25,IF($C$11=I$11,I25,IF($C$11=J$11,J25,IF($C$11=K$11,K25,IF($C$11=L$11,L25,IF($C$11=M$11,M25,N25)))))))) -> 180 | E25: 4º Sexenio | F25: 180 | G25: =+F25 -> 180 | H25: =+G25 -> 180 | I25: =+H25 -> 180 | J25: =+I25 -> 180 | K25: =+J25 -> 180 | L25: =+K25 -> 180 | M25: =+L25 -> 180 | N25: =+M25 -> 180 | Z25: 140.4 | AA25: =+Z25 -> 140.4 | AB25: =+AA25 -> 140.4 | AC25: =+AB25 -> 140.4 | AD25: =+AC25 -> 140.4 | AE25: =+AD25 -> 140.4 | AF25: =+AE25 -> 140.4 | AG25: =+AF25 -> 140.4 | AH25: =+AG25 -> 140.4
B26: 5º Sexenio | C26: =IF($C$11=$F$11,F26,IF($C$11=G$11,G26,IF($C$11=H$11,H26,IF($C$11=I$11,I26,IF($C$11=J$11,J26,IF($C$11=K$11,K26,IF($C$11=L$11,L26,IF($C$11=M$11,M26,N26)))))))) -> 70 | E26: 5º Sexenio | F26: 70 | G26: =+F26 -> 70 | H26: =+G26 -> 70 | I26: =+H26 -> 70 | J26: =+I26 -> 70 | K26: =+J26 -> 70 | L26: =+K26 -> 70 | M26: =+L26 -> 70 | N26: =+M26 -> 70 | Z26: 54.6 | AA26: =+Z26 -> 54.6 | AB26: =+AA26 -> 54.6 | AC26: =+AB26 -> 54.6 | AD26: =+AC26 -> 54.6 | AE26: =+AD26 -> 54.6 | AF26: =+AE26 -> 54.6 | AG26: =+AF26 -> 54.6 | AH26: =+AG26 -> 54.6
B27: Tutoría | C27: =IF($C$11=$F$11,F27,IF($C$11=G$11,G27,IF($C$11=H$11,H27,IF($C$11=I$11,I27,IF($C$11=J$11,J27,IF($C$11=K$11,K27,IF($C$11=L$11,L27,IF($C$11=M$11,M27,N27)))))))) -> 35 | E27: Tutoría | F27: 35 | G27: =+F27 -> 35 | H27: =+G27 -> 35 | I27: =+H27 -> 35 | J27: =+I27 -> 35 | K27: =+J27 -> 35 | L27: =+K27 -> 35 | M27: =+L27 -> 35
B28: Cargo directivo | C28: =IF($C$11=$F$11,F28,IF($C$11=G$11,G28,IF($C$11=H$11,H28,IF($C$11=I$11,I28,IF($C$11=J$11,J28,IF($C$11=K$11,K28,IF($C$11=L$11,L28,IF($C$11=M$11,M28,N28)))))))) -> 253.88 | E28: Cargo directivo | F28: =IF($C$1=F11,'Nómina mensual'!$G$29,0) -> 0 | G28: =IF($C$1=G11,'Nómina mensual'!$G$29,0) -> 0 | H28: =IF($C$1=H11,'Nómina mensual'!$G$29,0) -> 0 | I28: =IF($C$1=I11,'Nómina mensual'!$G$29,0) -> 253.88 | J28: =IF($C$1=J11,'Nómina mensual'!$G$29,0) -> 0 | K28: =IF($C$1=K11,'Nómina mensual'!$G$29,0) -> 0 | L28: =IF($C$1=L11,'Nómina mensual'!$G$29,0) -> 0 | M28: =IF($C$1=M11,'Nómina mensual'!$G$29,0) -> 0
B29: Residencia Isla Capitalina | C29: =IF($C$11=$F$11,F29,IF($C$11=G$11,G29,IF($C$11=H$11,H29,IF($C$11=I$11,I29,IF($C$11=J$11,J29,IF($C$11=K$11,K29,IF($C$11=L$11,L29,IF($C$11=M$11,M29,N29)))))))) -> 160.59 | E29: Residencia Isla Capitalina | F29: 144.55 | G29: =+F29 -> 144.55 | H29: =+G29 -> 144.55 | I29: 160.59 | J29: =+I29 -> 160.59 | K29: =+J29 -> 160.59 | L29: =+K29 -> 160.59 | M29: 180.67 | N29: 178.29
B30: Residencia Isla No Capitalina | C30: =IF($C$11=$F$11,F30,IF($C$11=G$11,G30,IF($C$11=H$11,H30,IF($C$11=I$11,I30,IF($C$11=J$11,J30,IF($C$11=K$11,K30,IF($C$11=L$11,L30,IF($C$11=M$11,M30,N30)))))))) -> 534.9 | E30: Residencia Isla No Capitalina | F30: 481.43 | G30: =+F30 -> 481.43 | H30: =+G30 -> 481.43 | I30: 534.9 | J30: =+I30 -> 534.9 | K30: =+J30 -> 534.9 | L30: =+K30 -> 534.9 | M30: 601.77 | N30: 594.06
B31: Trienios Residencia Isla No Capitalina | C31: =IF($C$11=$F$11,F31,IF($C$11=G$11,G31,IF($C$11=H$11,H31,IF($C$11=I$11,I31,IF($C$11=J$11,J31,IF($C$11=K$11,K31,IF($C$11=L$11,L31,IF($C$11=M$11,M31,N31)))))))) -> 37.63 | E31: Trienios Residencia Isla No Capitalina | F31: 33.84 | G31: =+F31 -> 33.84 | H31: =+G31 -> 33.84 | I31: 37.63 | J31: =+I31 -> 37.63 | K31: =+J31 -> 37.63 | L31: =+K31 -> 37.63 | M31: 42.25 | N31: 90.28
B32: Adicional maestros 1º y 2º ESO | C32: =IF($C$11=$F$11,F32,IF($C$11=G$11,G32,IF($C$11=H$11,H32,IF($C$11=I$11,I32,IF($C$11=J$11,J32,IF($C$11=K$11,K32,IF($C$11=L$11,L32,IF($C$11=M$11,M32,N32)))))))) -> 0 | E32: Adicional maestros 1º y 2º ESO | F32: 70.34
B33: Complemento mejora/especial dedicación | C33: =IF($C$11=$F$11,F33,IF($C$11=G$11,G33,IF($C$11=H$11,H33,IF($C$11=I$11,I33,IF($C$11=J$11,J33,IF($C$11=K$11,K33,IF($C$11=L$11,L33,IF($C$11=M$11,M33,N33)))))))) -> 0 | E33: Extra Adicional maestros 1º y 2º ESO | F33: 68.31
B34: Productividad semestral (Murcia) | C34: =IF($C$11=$F$11,F34,IF($C$11=G$11,G34,IF($C$11=H$11,H34,IF($C$11=I$11,I34,IF($C$11=J$11,J34,IF($C$11=K$11,K34,IF($C$11=L$11,L34,IF($C$11=M$11,M34,N34)))))))) -> 0 | E34: Productividad semestral (Murcia)
B35: Reducción 3% (Castilla la Mancha) | C35: =IF($C$11=$F$11,F35,IF($C$11=G$11,G35,IF($C$11=H$11,H35,IF($C$11=I$11,I35,IF($C$11=J$11,J35,IF($C$11=K$11,K35,IF($C$11=L$11,L35,IF($C$11=M$11,M35,N35)))))))) -> 0 | E35: Reducción 3% (Castilla la Mancha)
B36: Otros | C36: =IF($C$11=$F$11,F36,IF($C$11=G$11,G36,IF($C$11=H$11,H36,IF($C$11=I$11,I36,IF($C$11=J$11,J36,IF($C$11=K$11,K36,IF($C$11=L$11,L36,IF($C$11=M$11,M36,N36)))))))) -> 0 | E36: Otros
E37: Dirección
E38: Vicedirección
E39: Jefatura de Estudios
E40: Secretaría
B41: MUFACE | C41: =IF($C$11=$F$11,F41,IF($C$11=G$11,G41,IF($C$11=H$11,H41,IF($C$11=I$11,I41,IF($C$11=J$11,J41,IF($C$11=K$11,K41,IF($C$11=L$11,L41,IF($C$11=M$11,M41,N41)))))))) -> -51.68 | E41: MUFACE | F41: =+F77 -> -40.68 | G41: =+G77 -> -40.68 | H41: =+H77 -> -40.68 | I41: =+I77 -> -51.68 | J41: =+J77 -> -51.68 | K41: =+K77 -> -51.68 | L41: =+L77 -> -51.68 | M41: =+M77 -> -51.68 | N41: =+N77 -> -51.68
B42: Clases Pasivas | C42: =IF($C$11=$F$11,F42,IF($C$11=G$11,G42,IF($C$11=H$11,H42,IF($C$11=I$11,I42,IF($C$11=J$11,J42,IF($C$11=K$11,K42,IF($C$11=L$11,L42,IF($C$11=M$11,M42,N42)))))))) -> 118.04 | E42: Clases Pasivas | F42: =+F78 -> -92.9 | G42: =+G78 -> -92.9 | H42: =+H78 -> -92.9 | I42: =+I78 -> 118.04 | J42: =+J78 -> 118.04 | K42: =+K78 -> 118.04 | L42: =+L78 -> 118.04 | M42: =+M78 -> 118.04 | N42: =+N78 -> 118.04
B43: SUELDO BRUTO ANUAL | C43: =IF($C$11=$F$11,F43,IF($C$11=G$11,G43,IF($C$11=H$11,H43,IF($C$11=I$11,I43,IF($C$11=J$11,J43,IF($C$11=K$11,K43,IF($C$11=L$11,L43,IF($C$11=M$11,M43,N43)))))))) -> 50376.4 | E43: SUELDO BRUTO ANUAL | F43: =((+F14+F18+F19)*12)+(F16*INT($C$3/3)*12)+((F15+F18)*2)+((F20)*2)+(F17*INT($C$3/3)*2)+(F28*14)+(IF($C$6="si",(F30*12)+(F31*INT($C$3/3)*12),F29*12))+(IF($C$4="si",F32,0))+(((IF(INT($C$3/3)<6,F21,0))+(IF(AND(INT($C$3/6)>0,INT($C$3/6)<2),F22,0))+(IF(AND(INT($C$3/6)>1,INT($C$3/6)<3),F22+F23,0))+(IF(AND(INT($C$3/6)>2,INT($C$3/6)<4),F22+F23+F24,0))+(IF(AND(INT($C$3/6)>3,INT($C$3/6)<5),F22+F23+F24+F25,0))+(IF(INT($C$3/6)>4,F22+F23+F24+F25+F26,0)))*12)+(IF($C$7="si",F27*12,0))+(((IF(INT($C$3/3)<6,F21,0))+(IF(AND(INT($C$3/6)>0,INT($C$3/6)<2),Z22,0))+(IF(AND(INT($C$3/6)>1,INT($C$3/6)<3),Z22+Z23,0))+(IF(AND(INT($C$3/6)>2,INT($C$3/6)<4),Z22+Z23+Z24,0))+(IF(AND(INT($C$3/6)>3,INT($C$3/6)<5),Z22+Z23+Z24+Z25,0))+(IF(INT($C$3/6)>4,Z22+Z23+Z24+Z25+Z26,0)))*2)+(F33*12)+(F34*2) -> 43366.94 | G43: =((+G14+G18+G19)*12)+(G16*INT($C$3/3)*12)+((G15+G18)*2)+((G20)*2)+(G17*INT($C$3/3)*2)+(G28*14)+(IF($C$6="si",(G30*12)+(G31*INT($C$3/3)*12),G29*12))+(IF($C$4="si",G32,0))+(((IF(INT($C$3/3)<6,G21,0))+(IF(AND(INT($C$3/6)>0,INT($C$3/6)<2),G22,0))+(IF(AND(INT($C$3/6)>1,INT($C$3/6)<3),G22+G23,0))+(IF(AND(INT($C$3/6)>2,INT($C$3/6)<4),G22+G23+G24,0))+(IF(AND(INT($C$3/6)>3,INT($C$3/6)<5),G22+G23+G24+G25,0))+(IF(INT($C$3/6)>4,G22+G23+G24+G25+G26,0)))*12)+(IF($C$7="si",G27*12,0))+(((IF(INT($C$3/3)<6,G21,0))+(IF(AND(INT($C$3/6)>0,INT($C$3/6)<2),AA22,0))+(IF(AND(INT($C$3/6)>1,INT($C$3/6)<3),AA22+AA23,0))+(IF(AND(INT($C$3/6)>2,INT($C$3/6)<4),AA22+AA23+AA24,0))+(IF(AND(INT($C$3/6)>3,INT($C$3/6)<5),AA22+AA23+AA24+AA25,0))+(IF(INT($C$3/6)>4,AA22+AA23+AA24+AA25+AA26,0)))*2)+(G33*12)+(G34*2) -> 43830.16 | H43: =((+H14+H18+H19)*12)+(H16*INT($C$3/3)*12)+((H15+H18)*2)+((H20)*2)+(H17*INT($C$3/3)*2)+(H28*14)+(IF($C$6="si",(H30*12)+(H31*INT($C$3/3)*12),H29*12))+(IF($C$4="si",H32,0))+(((IF(INT($C$3/3)<6,H21,0))+(IF(AND(INT($C$3/6)>0,INT($C$3/6)<2),H22,0))+(IF(AND(INT($C$3/6)>1,INT($C$3/6)<3),H22+H23,0))+(IF(AND(INT($C$3/6)>2,INT($C$3/6)<4),H22+H23+H24,0))+(IF(AND(INT($C$3/6)>3,INT($C$3/6)<5),H22+H23+H24+H25,0))+(IF(INT($C$3/6)>4,H22+H23+H24+H25+H26,0)))*12)+(IF($C$7="si",H27*12,0))+(((IF(INT($C$3/3)<6,H21,0))+(IF(AND(INT($C$3/6)>0,INT($C$3/6)<2),AB22,0))+(IF(AND(INT($C$3/6)>1,INT($C$3/6)<3),AB22+AB23,0))+(IF(AND(INT($C$3/6)>2,INT($C$3/6)<4),AB22+AB23+AB24,0))+(IF(AND(INT($C$3/6)>3,INT($C$3/6)<5),AB22+AB23+AB24+AB25,0))+(IF(INT($C$3/6)>4,AB22+AB23+AB24+AB25+AB26,0)))*2)+(H33*12)+(H34*2) -> 43830.16 | I43: =((+I14+I18+I19)*12)+(I16*INT($C$3/3)*12)+((I15+I18)*2)+((I20)*2)+(I17*INT($C$3/3)*2)+(I28*14)+(IF($C$6="si",(I30*12)+(I31*INT($C$3/3)*12),I29*12))+(IF($C$4="si",I32,0))+(((IF(INT($C$3/3)<6,I21,0))+(IF(AND(INT($C$3/6)>0,INT($C$3/6)<2),I22,0))+(IF(AND(INT($C$3/6)>1,INT($C$3/6)<3),I22+I23,0))+(IF(AND(INT($C$3/6)>2,INT($C$3/6)<4),I22+I23+I24,0))+(IF(AND(INT($C$3/6)>3,INT($C$3/6)<5),I22+I23+I24+I25,0))+(IF(INT($C$3/6)>4,I22+I23+I24+I25+I26,0)))*12)+(IF($C$7="si",I27*12,0))+(((IF(INT($C$3/3)<6,I21,0))+(IF(AND(INT($C$3/6)>0,INT($C$3/6)<2),AC22,0))+(IF(AND(INT($C$3/6)>1,INT($C$3/6)<3),AC22+AC23,0))+(IF(AND(INT($C$3/6)>2,INT($C$3/6)<4),AC22+AC23+AC24,0))+(IF(AND(INT($C$3/6)>3,INT($C$3/6)<5),AC22+AC23+AC24+AC25,0))+(IF(INT($C$3/6)>4,AC22+AC23+AC24+AC25+AC26,0)))*2)+(I33*12)+(I34*2) -> 50376.4 | J43: =((+J14+J18+J19)*12)+(J16*INT($C$3/3)*12)+((J15+J18)*2)+((J20)*2)+(J17*INT($C$3/3)*2)+(J28*14)+(IF($C$6="si",(J30*12)+(J31*INT($C$3/3)*12),J29*12))+(IF($C$4="si",J32,0))+(((IF(INT($C$3/3)<6,J21,0))+(IF(AND(INT($C$3/6)>0,INT($C$3/6)<2),J22,0))+(IF(AND(INT($C$3/6)>1,INT($C$3/6)<3),J22+J23,0))+(IF(AND(INT($C$3/6)>2,INT($C$3/6)<4),J22+J23+J24,0))+(IF(AND(INT($C$3/6)>3,INT($C$3/6)<5),J22+J23+J24+J25,0))+(IF(INT($C$3/6)>4,J22+J23+J24+J25+J26,0)))*12)+(IF($C$7="si",J27*12,0))+(((IF(INT($C$3/3)<6,J21,0))+(IF(AND(INT($C$3/6)>0,INT($C$3/6)<2),AD22,0))+(IF(AND(INT($C$3/6)>1,INT($C$3/6)<3),AD22+AD23,0))+(IF(AND(INT($C$3/6)>2,INT($C$3/6)<4),AD22+AD23+AD24,0))+(IF(AND(INT($C$3/6)>3,INT($C$3/6)<5),AD22+AD23+AD24+AD25,0))+(IF(INT($C$3/6)>4,AD22+AD23+AD24+AD25+AD26,0)))*2)+(J33*12)+(J34*2) -> 46822.08 | K43: =((+K14+K18+K19)*12)+(K16*INT($C$3/3)*12)+((K15+K18)*2)+((K20)*2)+(K17*INT($C$3/3)*2)+(K28*14)+(IF($C$6="si",(K30*12)+(K31*INT($C$3/3)*12),K29*12))+(IF($C$4="si",K32,0))+(((IF(INT($C$3/3)<6,K21,0))+(IF(AND(INT($C$3/6)>0,INT($C$3/6)<2),K22,0))+(IF(AND(INT($C$3/6)>1,INT($C$3/6)<3),K22+K23,0))+(IF(AND(INT($C$3/6)>2,INT($C$3/6)<4),K22+K23+K24,0))+(IF(AND(INT($C$3/6)>3,INT($C$3/6)<5),K22+K23+K24+K25,0))+(IF(INT($C$3/6)>4,K22+K23+K24+K25+K26,0)))*12)+(IF($C$7="si",K27*12,0))+(((IF(INT($C$3/3)<6,K21,0))+(IF(AND(INT($C$3/6)>0,INT($C$3/6)<2),AE22,0))+(IF(AND(INT($C$3/6)>1,INT($C$3/6)<3),AE22+AE23,0))+(IF(AND(INT($C$3/6)>2,INT($C$3/6)<4),AE22+AE23+AE24,0))+(IF(AND(INT($C$3/6)>3,INT($C$3/6)<5),AE22+AE23+AE24+AE25,0))+(IF(INT($C$3/6)>4,AE22+AE23+AE24+AE25+AE26,0)))*2)+(K33*12)+(K34*2) -> 46822.08 | L43: =((+L14+L18+L19)*12)+(L16*INT($C$3/3)*12)+((L15+L18)*2)+((L20)*2)+(L17*INT($C$3/3)*2)+(L28*14)+(IF($C$6="si",(L30*12)+(L31*INT($C$3/3)*12),L29*12))+(IF($C$4="si",L32,0))+(((IF(INT($C$3/3)<6,L21,0))+(IF(AND(INT($C$3/6)>0,INT($C$3/6)<2),L22,0))+(IF(AND(INT($C$3/6)>1,INT($C$3/6)<3),L22+L23,0))+(IF(AND(INT($C$3/6)>2,INT($C$3/6)<4),L22+L23+L24,0))+(IF(AND(INT($C$3/6)>3,INT($C$3/6)<5),L22+L23+L24+L25,0))+(IF(INT($C$3/6)>4,L22+L23+L24+L25+L26,0)))*12)+(IF($C$7="si",L27*12,0))+(((IF(INT($C$3/3)<6,L21,0))+(IF(AND(INT($C$3/6)>0,INT($C$3/6)<2),AF22,0))+(IF(AND(INT($C$3/6)>1,INT($C$3/6)<3),AF22+AF23,0))+(IF(AND(INT($C$3/6)>2,INT($C$3/6)<4),AF22+AF23+AF24,0))+(IF(AND(INT($C$3/6)>3,INT($C$3/6)<5),AF22+AF23+AF24+AF25,0))+(IF(INT($C$3/6)>4,AF22+AF23+AF24+AF25+AF26,0)))*2)+(L33*12)+(L34*2) -> 46822.08 | M43: =((+M14+M18+M19)*12)+(M16*INT($C$3/3)*12)+((M15+M18)*2)+((M20)*2)+(M17*INT($C$3/3)*2)+(M28*14)+(IF($C$6="si",(M30*12)+(M31*INT($C$3/3)*12),M29*12))+(IF($C$4="si",M32,0))+(((IF(INT($C$3/3)<6,M21,0))+(IF(AND(INT($C$3/6)>0,INT($C$3/6)<2),M22,0))+(IF(AND(INT($C$3/6)>1,INT($C$3/6)<3),M22+M23,0))+(IF(AND(INT($C$3/6)>2,INT($C$3/6)<4),M22+M23+M24,0))+(IF(AND(INT($C$3/6)>3,INT($C$3/6)<5),M22+M23+M24+M25,0))+(IF(INT($C$3/6)>4,M22+M23+M24+M25+M26,0)))*12)+(IF($C$7="si",M27*12,0))+(((IF(INT($C$3/3)<6,M21,0))+(IF(AND(INT($C$3/6)>0,INT($C$3/6)<2),AG22,0))+(IF(AND(INT($C$3/6)>1,INT($C$3/6)<3),AG22+AG23,0))+(IF(AND(INT($C$3/6)>2,INT($C$3/6)<4),AG22+AG23+AG24,0))+(IF(AND(INT($C$3/6)>3,INT($C$3/6)<5),AG22+AG23+AG24+AG25,0))+(IF(INT($C$3/6)>4,AG22+AG23+AG24+AG25+AG26,0)))*2)+(M33*12)+(M34*2) -> 50502.94 | N43: =((+N14+N18+N19)*12)+(N16*INT($C$3/3)*12)+((N15+N18)*2)+((N20)*2)+(N17*INT($C$3/3)*2)+(N28*14)+(IF($C$6="si",(N30*12)+(N31*INT($C$3/3)*12),N29*12))+(IF($C$4="si",N32,0))+(((IF(INT($C$3/3)<6,N21,0))+(IF(AND(INT($C$3/6)>0,INT($C$3/6)<2),N22,0))+(IF(AND(INT($C$3/6)>1,INT($C$3/6)<3),N22+N23,0))+(IF(AND(INT($C$3/6)>2,INT($C$3/6)<4),N22+N23+N24,0))+(IF(AND(INT($C$3/6)>3,INT($C$3/6)<5),N22+N23+N24+N25,0))+(IF(INT($C$3/6)>4,N22+N23+N24+N25+N26,0)))*12)+(IF($C$7="si",N27*12,0))+(((IF(INT($C$3/3)<6,N21,0))+(IF(AND(INT($C$3/6)>0,INT($C$3/6)<2),AH22,0))+(IF(AND(INT($C$3/6)>1,INT($C$3/6)<3),AH22+AH23,0))+(IF(AND(INT($C$3/6)>2,INT($C$3/6)<4),AH22+AH23+AH24,0))+(IF(AND(INT($C$3/6)>3,INT($C$3/6)<5),AH22+AH23+AH24+AH25,0))+(IF(INT($C$3/6)>4,AH22+AH23+AH24+AH25+AH26,0)))*2)+(N33*12)+(N34*2) -> 58947.22
C50: =+E51 -> Andalucía
C51: =+$C$11 -> 590-Profesores Enseñanza Secundaria | E51: Andalucía | F51: 597-Maestros | G51: 591-Profesores Técnicos de Formación Profesional | H51: 596-Maestros de Taller de Artes Plásticas y Diseño | I51: 590-Profesores Enseñanza Secundaria | J51: 592-Profesores de Escuelas Oficiales de Idiomas | K51: 594-Profesores de Música y Artes Escénicas | L51: 595-Profesores de Artes Plásticas y Diseño | M51: 511-Catedráticos | N51: 510-Inspección | O51: ACTUALIZADO 02/26 (con +1,5%) | Q51: A2 | W51: A1
B52: Grupo | C52: =IF($C$11=$F$11,F52,IF($C$11=G$11,G52,IF($C$11=H$11,H52,IF($C$11=I$11,I52,IF($C$11=J$11,J52,IF($C$11=K$11,K52,IF($C$11=L$11,L52,IF($C$11=M$11,M52,N52)))))))) -> A1 | E52: Grupo | F52: A2 | G52: A2 | H52: A2 | I52: A1 | J52: A1 | K52: A1 | L52: A1 | M52: A1 | N52: A1 | R52: Sin cargo | S52: Dirección | T52: Vicedirección | U52: Jefatura de Estudios | V52: Secretaría | W52: Sin cargo | X52: Dirección | Y52: Vicedirección | Z52: Jefatura de Estudios | AA52: Secretaría
B53: =+E53 -> Nivel | C53: =IF($C$11=$F$11,F53,IF($C$11=G$11,G53,IF($C$11=H$11,H53,IF($C$11=I$11,I53,IF($C$11=J$11,J53,IF($C$11=K$11,K53,IF($C$11=L$11,L53,IF($C$11=M$11,M53,N53)))))))) -> 24 | E53: Nivel | F53: 21 | G53: 24 | H53: 24 | I53: 24 | J53: 24 | K53: 24 | L53: 24 | M53: 26 | N53: 26 | Q53: A | R53: 0 | S53: 803.31 | U53: 442.01 | V53: =U53 -> 442.01 | W53: 0 | X53: 994.55 | Y53: 524.39 | Z53: 200.53 | AA53: =Z53 -> 200.53
B54: Sueldo Base | C54: =IF($C$11=$F$11,F54,IF($C$11=G$11,G54,IF($C$11=H$11,H54,IF($C$11=I$11,I54,IF($C$11=J$11,J54,IF($C$11=K$11,K54,IF($C$11=L$11,L54,IF($C$11=M$11,M54,N54)))))))) -> 1387.24 | E54: Sueldo Base | F54: 1199.52 | G54: =+F54 -> 1199.52 | H54: =+G54 -> 1199.52 | I54: 1387.24 | J54: =+I54 -> 1387.24 | K54: =+J54 -> 1387.24 | L54: =+K54 -> 1387.24 | M54: =+L54 -> 1387.24 | N54: =+M54 -> 1387.24 | Q54: B | R54: 0 | S54: 703.42 | U54: 355.85 | V54: =U54 -> 355.85 | W54: 0 | X54: 797.63 | Y54: 437.01 | Z54: 200.53 | AA54: =Z54 -> 200.53
B55: Extra Sueldo Base | C55: =IF($C$11=$F$11,F55,IF($C$11=G$11,G55,IF($C$11=H$11,H55,IF($C$11=I$11,I55,IF($C$11=J$11,J55,IF($C$11=K$11,K55,IF($C$11=L$11,L55,IF($C$11=M$11,M55,N55)))))))) -> 856.05 | E55: Extra Sueldo Base | F55: 874.83 | G55: =+F55 -> 874.83 | H55: =+G55 -> 874.83 | I55: 856.05 | J55: =+I55 -> 856.05 | K55: =+J55 -> 856.05 | L55: =+K55 -> 856.05 | M55: =+L55 -> 856.05 | N55: =+M55 -> 856.05 | Q55: C | R55: 0 | S55: 505.11 | U55: 269.68 | V55: =U55 -> 269.68 | W55: 0 | X55: 697.7 | Y55: 350.9 | Z55: 200.53 | AA55: =Z55 -> 200.53
B56: Trienios | C56: =IF($C$11=$F$11,F56,IF($C$11=G$11,G56,IF($C$11=H$11,H56,IF($C$11=I$11,I56,IF($C$11=J$11,J56,IF($C$11=K$11,K56,IF($C$11=L$11,L56,IF($C$11=M$11,M56,N56)))))))) -> 53.39 | E56: Trienios | F56: 43.54 | G56: =+F56 -> 43.54 | H56: =+G56 -> 43.54 | I56: 53.39 | J56: =+I56 -> 53.39 | K56: =+J56 -> 53.39 | L56: =+K56 -> 53.39 | M56: =+L56 -> 53.39 | N56: =+M56 -> 53.39 | Q56: D | R56: 0 | S56: 308.2 | U56: 182.31 | V56: =U56 -> 182.31 | W56: 0 | AA56: =Z56 -> 0
B57: Extra Trienio | C57: =IF($C$11=$F$11,F57,IF($C$11=G$11,G57,IF($C$11=H$11,H57,IF($C$11=I$11,I57,IF($C$11=J$11,J57,IF($C$11=K$11,K57,IF($C$11=L$11,L57,IF($C$11=M$11,M57,N57)))))))) -> 32.96 | E57: Extra Trienio | F57: 31.74 | G57: =+F57 -> 31.74 | H57: =+G57 -> 31.74 | I57: 32.96 | J57: =+I57 -> 32.96 | K57: =+J57 -> 32.96 | L57: =+K57 -> 32.96 | M57: =+L57 -> 32.96 | N57: =+M57 -> 32.96 | Q57: E | R57: 0 | S57: 208.36 | W57: 0
B58: Complemento Destino | C58: =IF($C$11=$F$11,F58,IF($C$11=G$11,G58,IF($C$11=H$11,H58,IF($C$11=I$11,I58,IF($C$11=J$11,J58,IF($C$11=K$11,K58,IF($C$11=L$11,L58,IF($C$11=M$11,M58,N58)))))))) -> 729.14 | E58: Complemento Destino | F58: 592.11 | G58: 729.14 | H58: =+G58 -> 729.14 | I58: =+H58 -> 729.14 | J58: =+I58 -> 729.14 | K58: =+J58 -> 729.14 | L58: =+K58 -> 729.14 | M58: 873.38 | N58: =+M58 -> 873.38 | Q58: F | R58: 0 | W58: 0
B59: Complemento Específico | C59: =IF($C$11=$F$11,F59,IF($C$11=G$11,G59,IF($C$11=H$11,H59,IF($C$11=I$11,I59,IF($C$11=J$11,J59,IF($C$11=K$11,K59,IF($C$11=L$11,L59,IF($C$11=M$11,M59,N59)))))))) -> 881.46 | E59: Complemento Específico | F59: 857.3 | G59: 881.46 | H59: =+G59 -> 881.46 | I59: =+H59 -> 881.46 | J59: =+I59 -> 881.46 | K59: =+J59 -> 881.46 | L59: =+K59 -> 881.46 | M59: =+L59 -> 881.46 | N59: 2175.81
B60: Complemento Específico Autonómico | C60: =IF($C$11=$F$11,F60,IF($C$11=G$11,G60,IF($C$11=H$11,H60,IF($C$11=I$11,I60,IF($C$11=J$11,J60,IF($C$11=K$11,K60,IF($C$11=L$11,L60,IF($C$11=M$11,M60,N60)))))))) -> 0 | E60: Complemento Específico Autonómico | M60: 62.01 | O60: Complemento nivelador catedráticos
B61: Sin sexenio | C61: =IF($C$11=$F$11,F61,IF($C$11=G$11,G61,IF($C$11=H$11,H61,IF($C$11=I$11,I61,IF($C$11=J$11,J61,IF($C$11=K$11,K61,IF($C$11=L$11,L61,IF($C$11=M$11,M61,N61)))))))) -> 0 | E61: Sin sexenio
B62: 1º Sexenio | C62: =IF($C$11=$F$11,F62,IF($C$11=G$11,G62,IF($C$11=H$11,H62,IF($C$11=I$11,I62,IF($C$11=J$11,J62,IF($C$11=K$11,K62,IF($C$11=L$11,L62,IF($C$11=M$11,M62,N62)))))))) -> 85.62 | E62: 1º Sexenio | F62: 85.62 | G62: =+F62 -> 85.62 | H62: =+G62 -> 85.62 | I62: =+H62 -> 85.62 | J62: =+I62 -> 85.62 | K62: =+J62 -> 85.62 | L62: =+K62 -> 85.62 | M62: =+L62 -> 85.62 | N62: =+M62 -> 85.62
B63: 2º Sexenio | C63: =IF($C$11=$F$11,F63,IF($C$11=G$11,G63,IF($C$11=H$11,H63,IF($C$11=I$11,I63,IF($C$11=J$11,J63,IF($C$11=K$11,K63,IF($C$11=L$11,L63,IF($C$11=M$11,M63,N63)))))))) -> 99.51 | E63: 2º Sexenio | F63: 99.51 | G63: =+F63 -> 99.51 | H63: =+G63 -> 99.51 | I63: =+H63 -> 99.51 | J63: =+I63 -> 99.51 | K63: =+J63 -> 99.51 | L63: =+K63 -> 99.51 | M63: =+L63 -> 99.51 | N63: =+M63 -> 99.51
B64: 3º Sexenio | C64: =IF($C$11=$F$11,F64,IF($C$11=G$11,G64,IF($C$11=H$11,H64,IF($C$11=I$11,I64,IF($C$11=J$11,J64,IF($C$11=K$11,K64,IF($C$11=L$11,L64,IF($C$11=M$11,M64,N64)))))))) -> 127.77 | E64: 3º Sexenio | F64: 127.77 | G64: =+F64 -> 127.77 | H64: =+G64 -> 127.77 | I64: =+H64 -> 127.77 | J64: =+I64 -> 127.77 | K64: =+J64 -> 127.77 | L64: =+K64 -> 127.77 | M64: =+L64 -> 127.77 | N64: =+M64 -> 127.77
B65: 4º Sexenio | C65: =IF($C$11=$F$11,F65,IF($C$11=G$11,G65,IF($C$11=H$11,H65,IF($C$11=I$11,I65,IF($C$11=J$11,J65,IF($C$11=K$11,K65,IF($C$11=L$11,L65,IF($C$11=M$11,M65,N65)))))))) -> 162.29 | E65: 4º Sexenio | F65: 162.29 | G65: =+F65 -> 162.29 | H65: =+G65 -> 162.29 | I65: =+H65 -> 162.29 | J65: =+I65 -> 162.29 | K65: =+J65 -> 162.29 | L65: =+K65 -> 162.29 | M65: =+L65 -> 162.29 | N65: =+M65 -> 162.29
B66: 5º Sexenio | C66: =IF($C$11=$F$11,F66,IF($C$11=G$11,G66,IF($C$11=H$11,H66,IF($C$11=I$11,I66,IF($C$11=J$11,J66,IF($C$11=K$11,K66,IF($C$11=L$11,L66,IF($C$11=M$11,M66,N66)))))))) -> 63.4 | E66: 5º Sexenio | F66: 63.4 | G66: =+F66 -> 63.4 | H66: =+G66 -> 63.4 | I66: =+H66 -> 63.4 | J66: =+I66 -> 63.4 | K66: =+J66 -> 63.4 | L66: =+K66 -> 63.4 | M66: =+L66 -> 63.4 | N66: =+M66 -> 63.4
B67: Tutoría | C67: =IF($C$11=$F$11,F67,IF($C$11=G$11,G67,IF($C$11=H$11,H67,IF($C$11=I$11,I67,IF($C$11=J$11,J67,IF($C$11=K$11,K67,IF($C$11=L$11,L67,IF($C$11=M$11,M67,N67)))))))) -> 31.97 | E67: Tutoría | F67: 31.97 | G67: =+F67 -> 31.97 | H67: =+G67 -> 31.97 | I67: =+H67 -> 31.97 | J67: =+I67 -> 31.97 | K67: =+J67 -> 31.97 | L67: =+K67 -> 31.97 | M67: =+L67 -> 31.97
B68: Cargo directivo | C68: =IF($C$11=$F$11,F68,IF($C$11=G$11,G68,IF($C$11=H$11,H68,IF($C$11=I$11,I68,IF($C$11=J$11,J68,IF($C$11=K$11,K68,IF($C$11=L$11,L68,IF($C$11=M$11,M68,N68)))))))) -> 350.9 | E68: Cargo directivo | F68: =IF($C$1=F51,'Nómina mensual'!$C$29,0) -> 0 | G68: =IF($C$1=G51,'Nómina mensual'!$C$29,0) -> 0 | H68: =IF($C$1=H51,'Nómina mensual'!$C$29,0) -> 0 | I68: =IF($C$1=I51,'Nómina mensual'!$C$29,0) -> 350.9 | J68: =IF($C$1=J51,'Nómina mensual'!$C$29,0) -> 0 | K68: =IF($C$1=K51,'Nómina mensual'!$C$29,0) -> 0 | L68: =IF($C$1=L51,'Nómina mensual'!$C$29,0) -> 0 | M68: =IF($C$1=M51,'Nómina mensual'!$C$29,0) -> 0
B69: Residencia Isla Capitalina | C69: =IF($C$11=$F$11,F69,IF($C$11=G$11,G69,IF($C$11=H$11,H69,IF($C$11=I$11,I69,IF($C$11=J$11,J69,IF($C$11=K$11,K69,IF($C$11=L$11,L69,IF($C$11=M$11,M69,N69)))))))) -> 0 | E69: Residencia Isla Capitalina
B70: Residencia Isla No Capitalina | C70: =IF($C$11=$F$11,F70,IF($C$11=G$11,G70,IF($C$11=H$11,H70,IF($C$11=I$11,I70,IF($C$11=J$11,J70,IF($C$11=K$11,K70,IF($C$11=L$11,L70,IF($C$11=M$11,M70,N70)))))))) -> 0 | E70: Residencia Isla No Capitalina
B71: Trienios Residencia Isla No Capitalina | C71: =IF($C$11=$F$11,F71,IF($C$11=G$11,G71,IF($C$11=H$11,H71,IF($C$11=I$11,I71,IF($C$11=J$11,J71,IF($C$11=K$11,K71,IF($C$11=L$11,L71,IF($C$11=M$11,M71,N71)))))))) -> 0 | E71: Trienios Residencia Isla No Capitalina
B72: Adicional maestros 1º y 2º ESO | C72: =IF($C$11=$F$11,F72,IF($C$11=G$11,G72,IF($C$11=H$11,H72,IF($C$11=I$11,I72,IF($C$11=J$11,J72,IF($C$11=K$11,K72,IF($C$11=L$11,L72,IF($C$11=M$11,M72,N72)))))))) -> 0 | E72: Adicional maestros 1º y 2º ESO | F72: =G58-F58 -> 137.03 | O72: FALTA MAESTROS EN LA ESO
B73: Complemento mejora/especial dedicación | C73: =IF($C$11=$F$11,F73,IF($C$11=G$11,G73,IF($C$11=H$11,H73,IF($C$11=I$11,I73,IF($C$11=J$11,J73,IF($C$11=K$11,K73,IF($C$11=L$11,L73,IF($C$11=M$11,M73,N73)))))))) -> 0 | E73: Complemento mejora/especial dedicación
B74: Productividad semestral (Murcia) | C74: =IF($C$11=$F$11,F74,IF($C$11=G$11,G74,IF($C$11=H$11,H74,IF($C$11=I$11,I74,IF($C$11=J$11,J74,IF($C$11=K$11,K74,IF($C$11=L$11,L74,IF($C$11=M$11,M74,N74)))))))) -> 0 | E74: Productividad semestral (Murcia)
B75: Reducción 3% (Castilla la Mancha) | C75: =IF($C$11=$F$11,F75,IF($C$11=G$11,G75,IF($C$11=H$11,H75,IF($C$11=I$11,I75,IF($C$11=J$11,J75,IF($C$11=K$11,K75,IF($C$11=L$11,L75,IF($C$11=M$11,M75,N75)))))))) -> 0 | E75: Reducción 3% (Castilla la Mancha)
B76: Otros | C76: =IF($C$11=$F$11,F76,IF($C$11=G$11,G76,IF($C$11=H$11,H76,IF($C$11=I$11,I76,IF($C$11=J$11,J76,IF($C$11=K$11,K76,IF($C$11=L$11,L76,IF($C$11=M$11,M76,N76)))))))) -> 0 | E76: Otros
B77: MUFACE | C77: =IF($C$11=$F$11,F77,IF($C$11=G$11,G77,IF($C$11=H$11,H77,IF($C$11=I$11,I77,IF($C$11=J$11,J77,IF($C$11=K$11,K77,IF($C$11=L$11,L77,IF($C$11=M$11,M77,N77)))))))) -> -51.68 | E77: MUFACE | F77: -40.68 | G77: =+F77 -> -40.68 | H77: =+G77 -> -40.68 | I77: -51.68 | J77: =+I77 -> -51.68 | K77: =+J77 -> -51.68 | L77: =+K77 -> -51.68 | M77: =+L77 -> -51.68 | N77: =+M77 -> -51.68
B78: Clases Pasivas | C78: =IF($C$11=$F$11,F78,IF($C$11=G$11,G78,IF($C$11=H$11,H78,IF($C$11=I$11,I78,IF($C$11=J$11,J78,IF($C$11=K$11,K78,IF($C$11=L$11,L78,IF($C$11=M$11,M78,N78)))))))) -> 118.04 | E78: Clases Pasivas | F78: -92.9 | G78: =+F78 -> -92.9 | H78: =+G78 -> -92.9 | I78: 118.04 | J78: =+I78 -> 118.04 | K78: =+J78 -> 118.04 | L78: =+K78 -> 118.04 | M78: =+L78 -> 118.04 | N78: =+M78 -> 118.04
B79: SUELDO BRUTO ANUAL | C79: =IF($C$11=$F$11,F79,IF($C$11=G$11,G79,IF($C$11=H$11,H79,IF($C$11=I$11,I79,IF($C$11=J$11,J79,IF($C$11=K$11,K79,IF($C$11=L$11,L79,IF($C$11=M$11,M79,N79)))))))) -> 46526.58 | E79: SUELDO BRUTO ANUAL | F79: =((+F54+F58+F59+F60)*12)+(F56*INT($C$3/3)*12)+((F55+F58)*2)+((F59+F60)*2)+(F57*INT($C$3/3)*2)+(F68*14)+(IF($C$6="s",,F69*12))+(IF($C$4="s",F72,0))+(IF($C$7="s",F67*12,0))++(((IF(INT($C$3/3)<6,F61,0))+(F73*12)+(F74*2)))+F80*14 -> 37021.6 | G79: =((+G54+G58+G59+G60)*12)+(G56*INT($C$3/3)*12)+((G55+G58)*2)+((G59+G60)*2)+(G57*INT($C$3/3)*2)+(G68*14)+(IF($C$6="s",,G69*12))+(IF($C$4="s",G72,0))+(IF($C$7="s",G67*12,0))++(((IF(INT($C$3/3)<6,G61,0))+(G73*12)+(G74*2)))+G80*14 -> 39278.26 | H79: =((+H54+H58+H59+H60)*12)+(H56*INT($C$3/3)*12)+((H55+H58)*2)+((H59+H60)*2)+(H57*INT($C$3/3)*2)+(H68*14)+(IF($C$6="s",,H69*12))+(IF($C$4="s",H72,0))+(IF($C$7="s",H67*12,0))++(((IF(INT($C$3/3)<6,H61,0))+(H73*12)+(H74*2)))+H80*14 -> 39278.26 | I79: =((+I54+I58+I59+I60)*12)+(I56*INT($C$3/3)*12)+((I55+I58)*2)+((I59+I60)*2)+(I57*INT($C$3/3)*2)+(I68*14)+(IF($C$6="s",,I69*12))+(IF($C$4="s",I72,0))+(IF($C$7="s",I67*12,0))++(((IF(INT($C$3/3)<6,I61,0))+(I73*12)+(I74*2)))+I80*14 -> 46526.58 | J79: =((+J54+J58+J59+J60)*12)+(J56*INT($C$3/3)*12)+((J55+J58)*2)+((J59+J60)*2)+(J57*INT($C$3/3)*2)+(J68*14)+(IF($C$6="s",,J69*12))+(IF($C$4="s",J72,0))+(IF($C$7="s",J67*12,0))++(((IF(INT($C$3/3)<6,J61,0))+(J73*12)+(J74*2)))+J80*14 -> 41613.98 | K79: =((+K54+K58+K59+K60)*12)+(K56*INT($C$3/3)*12)+((K55+K58)*2)+((K59+K60)*2)+(K57*INT($C$3/3)*2)+(K68*14)+(IF($C$6="s",,K69*12))+(IF($C$4="s",K72,0))+(IF($C$7="s",K67*12,0))++(((IF(INT($C$3/3)<6,K61,0))+(K73*12)+(K74*2)))+K80*14 -> 41613.98 | L79: =((+L54+L58+L59+L60)*12)+(L56*INT($C$3/3)*12)+((L55+L58)*2)+((L59+L60)*2)+(L57*INT($C$3/3)*2)+(L68*14)+(IF($C$6="s",,L69*12))+(IF($C$4="s",L72,0))+(IF($C$7="s",L67*12,0))++(((IF(INT($C$3/3)<6,L61,0))+(L73*12)+(L74*2)))+L80*14 -> 41613.98 | M79: =((+M54+M58+M59+M60)*12)+(M56*INT($C$3/3)*12)+((M55+M58)*2)+((M59+M60)*2)+(M57*INT($C$3/3)*2)+(M68*14)+(IF($C$6="s",,M69*12))+(IF($C$4="s",M72,0))+(IF($C$7="s",M67*12,0))++(((IF(INT($C$3/3)<6,M61,0))+(M73*12)+(M74*2)))+M80*14 -> 44501.48 | N79: =((+N54+N58+N59+N60)*12)+(N56*INT($C$3/3)*12)+((N55+N58)*2)+((N59+N60)*2)+(N57*INT($C$3/3)*2)+(N68*14)+(IF($C$6="s",,N69*12))+(IF($C$4="s",N72,0))+(IF($C$7="s",N67*12,0))++(((IF(INT($C$3/3)<6,N61,0))+(N73*12)+(N74*2)))+N80*14 -> 61754.24
E80: Corresponde por sexenio: | F80: =IF($C$3/6>=5,SUM(F62:F66),IF($C$3/6>=4,SUM(F63:F66),IF($C$3/6>=3,SUM(F62:F64),IF($C$3/6>=2,SUM(F62:F63),IF($C$3/6>=1,F62,F61))))) -> 0 | G80: =IF($C$3/6>=5,SUM(G62:G66),IF($C$3/6>=4,SUM(G63:G66),IF($C$3/6>=3,SUM(G62:G64),IF($C$3/6>=2,SUM(G62:G63),IF($C$3/6>=1,G62,G61))))) -> 0 | H80: =IF($C$3/6>=5,SUM(H62:H66),IF($C$3/6>=4,SUM(H63:H66),IF($C$3/6>=3,SUM(H62:H64),IF($C$3/6>=2,SUM(H62:H63),IF($C$3/6>=1,H62,H61))))) -> 0 | I80: =IF($C$3/6>=5,SUM(I62:I66),IF($C$3/6>=4,SUM(I63:I66),IF($C$3/6>=3,SUM(I62:I64),IF($C$3/6>=2,SUM(I62:I63),IF($C$3/6>=1,I62,I61))))) -> 0 | J80: =IF($C$3/6>=5,SUM(J62:J66),IF($C$3/6>=4,SUM(J63:J66),IF($C$3/6>=3,SUM(J62:J64),IF($C$3/6>=2,SUM(J62:J63),IF($C$3/6>=1,J62,J61))))) -> 0 | K80: =IF($C$3/6>=5,SUM(K62:K66),IF($C$3/6>=4,SUM(K63:K66),IF($C$3/6>=3,SUM(K62:K64),IF($C$3/6>=2,SUM(K62:K63),IF($C$3/6>=1,K62,K61))))) -> 0 | L80: =IF($C$3/6>=5,SUM(L62:L66),IF($C$3/6>=4,SUM(L63:L66),IF($C$3/6>=3,SUM(L62:L64),IF($C$3/6>=2,SUM(L62:L63),IF($C$3/6>=1,L62,L61))))) -> 0 | M80: =IF($C$3/6>=5,SUM(M62:M66),IF($C$3/6>=4,SUM(M63:M66),IF($C$3/6>=3,SUM(M62:M64),IF($C$3/6>=2,SUM(M62:M63),IF($C$3/6>=1,M62,M61))))) -> 0 | N80: =IF($C$3/6>=5,SUM(N62:N66),IF($C$3/6>=4,SUM(N63:N66),IF($C$3/6>=3,SUM(N62:N64),IF($C$3/6>=2,SUM(N62:N63),IF($C$3/6>=1,N62,N61))))) -> 0
C86: =+E87 -> Aragón
C87: =+$C$11 -> 590-Profesores Enseñanza Secundaria | E87: Aragón | F87: 597-Maestros | G87: 591-Profesores Técnicos de Formación Profesional | H87: 596-Maestros de Taller de Artes Plásticas y Diseño | I87: 590-Profesores Enseñanza Secundaria | J87: 592-Profesores de Escuelas Oficiales de Idiomas | K87: 594-Profesores de Música y Artes Escénicas | L87: 595-Profesores de Artes Plásticas y Diseño | M87: 511-Catedráticos | N87: 510-Inspección | O87: ACTUALIZADO 02/26 | Q87: A2 | W87: A1
B88: Grupo | C88: =IF($C$11=$F$11,F88,IF($C$11=G$11,G88,IF($C$11=H$11,H88,IF($C$11=I$11,I88,IF($C$11=J$11,J88,IF($C$11=K$11,K88,IF($C$11=L$11,L88,IF($C$11=M$11,M88,N88)))))))) -> A1 | E88: Grupo | F88: A2 | G88: A2 | H88: A2 | I88: A1 | J88: A1 | K88: A1 | L88: A1 | M88: A1 | N88: A1 | R88: Sin cargo | S88: Dirección | T88: Vicedirección | U88: Jefatura de Estudios | V88: Secretaría | W88: Sin cargo | X88: Dirección | Y88: Vicedirección | Z88: Jefatura de Estudios | AA88: Secretaría
B89: =+E89 -> Nivel | C89: =IF($C$11=$F$11,F89,IF($C$11=G$11,G89,IF($C$11=H$11,H89,IF($C$11=I$11,I89,IF($C$11=J$11,J89,IF($C$11=K$11,K89,IF($C$11=L$11,L89,IF($C$11=M$11,M89,N89)))))))) -> 24 | E89: Nivel | F89: 21 | G89: 24 | H89: 24 | I89: 24 | J89: 24 | K89: 24 | L89: 24 | M89: 26 | N89: 26 | Q89: A | R89: 0 | S89: 737.14 | U89: 305.31 | V89: =U89 -> 305.31 | W89: 0 | X89: 899.46 | Y89: 459.72 | Z89: =Y89 -> 459.72 | AA89: =Z89 -> 459.72
B90: Sueldo Base | C90: =IF($C$11=$F$11,F90,IF($C$11=G$11,G90,IF($C$11=H$11,H90,IF($C$11=I$11,I90,IF($C$11=J$11,J90,IF($C$11=K$11,K90,IF($C$11=L$11,L90,IF($C$11=M$11,M90,N90)))))))) -> 1387.24 | E90: Sueldo Base | F90: =+F54 -> 1199.52 | G90: =+G54 -> 1199.52 | H90: =+H54 -> 1199.52 | I90: =+I54 -> 1387.24 | J90: =+I90 -> 1387.24 | K90: =+J90 -> 1387.24 | L90: =+K90 -> 1387.24 | M90: =+L90 -> 1387.24 | N90: =+M90 -> 1387.24 | Q90: B | R90: 0 | S90: 667.27 | U90: 286.88 | V90: =U90 -> 286.88 | W90: 0 | X90: 774.74 | Y90: 454.5 | Z90: =Y90 -> 454.5 | AA90: =Z90 -> 454.5
B91: Extra Sueldo Base | C91: =IF($C$11=$F$11,F91,IF($C$11=G$11,G91,IF($C$11=H$11,H91,IF($C$11=I$11,I91,IF($C$11=J$11,J91,IF($C$11=K$11,K91,IF($C$11=L$11,L91,IF($C$11=M$11,M91,N91)))))))) -> 856.05 | E91: Extra Sueldo Base | F91: =+F55 -> 874.83 | G91: =+G55 -> 874.83 | H91: =+H55 -> 874.83 | I91: =+I55 -> 856.05 | J91: =+I91 -> 856.05 | K91: =+J91 -> 856.05 | L91: =+K91 -> 856.05 | M91: =+L91 -> 856.05 | N91: =+M91 -> 856.05 | Q91: C | R91: 0 | S91: 482.88 | U91: 277.7 | V91: =U91 -> 277.7 | W91: 0 | X91: 701.3 | Y91: 332.96 | Z91: =Y91 -> 332.96 | AA91: =Z91 -> 332.96
B92: Trienios | C92: =IF($C$11=$F$11,F92,IF($C$11=G$11,G92,IF($C$11=H$11,H92,IF($C$11=I$11,I92,IF($C$11=J$11,J92,IF($C$11=K$11,K92,IF($C$11=L$11,L92,IF($C$11=M$11,M92,N92)))))))) -> 53.39 | E92: Trienios | F92: =+F56 -> 43.54 | G92: =+G56 -> 43.54 | H92: =+H56 -> 43.54 | I92: =+I56 -> 53.39 | J92: =+I92 -> 53.39 | K92: =+J92 -> 53.39 | L92: =+K92 -> 53.39 | M92: =+L92 -> 53.39 | N92: =+M92 -> 53.39 | Q92: D | R92: 0 | S92: 367.22 | U92: 204.03 | V92: =U92 -> 204.03 | W92: 0 | X92: 634.87 | Y92: 286.88 | Z92: =Y92 -> 286.88 | AA92: =Z92 -> 286.88
B93: Extra Trienio | C93: =IF($C$11=$F$11,F93,IF($C$11=G$11,G93,IF($C$11=H$11,H93,IF($C$11=I$11,I93,IF($C$11=J$11,J93,IF($C$11=K$11,K93,IF($C$11=L$11,L93,IF($C$11=M$11,M93,N93)))))))) -> 32.96 | E93: Extra Trienio | F93: =+F57 -> 31.74 | G93: =+G57 -> 31.74 | H93: =+H57 -> 31.74 | I93: =+I57 -> 32.96 | J93: =+I93 -> 32.96 | K93: =+J93 -> 32.96 | L93: =+K93 -> 32.96 | M93: =+L93 -> 32.96 | N93: =+M93 -> 32.96 | O93: Inspección | Q93: E | R93: 0 | S93: 269.62 | V93: 171.78 | W93: 0 | Z93: =Z92 -> 286.88 | AA93: =Z93 -> 286.88
B94: Complemento Destino | C94: =IF($C$11=$F$11,F94,IF($C$11=G$11,G94,IF($C$11=H$11,H94,IF($C$11=I$11,I94,IF($C$11=J$11,J94,IF($C$11=K$11,K94,IF($C$11=L$11,L94,IF($C$11=M$11,M94,N94)))))))) -> 729.14 | E94: Complemento Destino | F94: =+F58 -> 592.11 | G94: =+G58 -> 729.14 | H94: =+H58 -> 729.14 | I94: =+I58 -> 729.14 | J94: =+J58 -> 729.14 | K94: =+K58 -> 729.14 | L94: =+L58 -> 729.14 | M94: =+M58 -> 873.38 | N94: =+N58 -> 873.38 | O94: C. especifico | Q94: F | R94: 0 | S94: 171.91 | W94: 0
B95: Complemento Específico | C95: =IF($C$11=$F$11,F95,IF($C$11=G$11,G95,IF($C$11=H$11,H95,IF($C$11=I$11,I95,IF($C$11=J$11,J95,IF($C$11=K$11,K95,IF($C$11=L$11,L95,IF($C$11=M$11,M95,N95)))))))) -> 756.22 | E95: Complemento Específico | F95: 740.23 | G95: =F95 -> 740.23 | H95: =+G95 -> 740.23 | I95: 756.22 | J95: =+I95 -> 756.22 | K95: =+J95 -> 756.22 | L95: =+K95 -> 756.22 | M95: 762.09 | N95: =O95 -> 808.69 | O95: 808.69
B96: Complemento Específico Autonómico | C96: =IF($C$11=$F$11,F96,IF($C$11=G$11,G96,IF($C$11=H$11,H96,IF($C$11=I$11,I96,IF($C$11=J$11,J96,IF($C$11=K$11,K96,IF($C$11=L$11,L96,IF($C$11=M$11,M96,N96)))))))) -> 680.598 | E96: EXTRA Complemento Específico | F96: =0.9*F95 -> 666.207 | G96: =0.9*G95 -> 666.207 | H96: =+G96 -> 666.207 | I96: =0.9*I95 -> 680.598 | J96: =+I96 -> 680.598 | K96: =+J96 -> 680.598 | L96: =+K96 -> 680.598 | M96: =0.9*M95 -> 685.881 | N96: =O96 -> 727.821 | O96: =0.9*O95 -> 727.821
B97: Sin sexenio | C97: =IF($C$11=$F$11,F97,IF($C$11=G$11,G97,IF($C$11=H$11,H97,IF($C$11=I$11,I97,IF($C$11=J$11,J97,IF($C$11=K$11,K97,IF($C$11=L$11,L97,IF($C$11=M$11,M97,N97)))))))) -> 0 | E97: Sin sexenio | AB97: SEXENIOS EXTRAS:
B98: 1º Sexenio | C98: =IF($C$11=$F$11,F98,IF($C$11=G$11,G98,IF($C$11=H$11,H98,IF($C$11=I$11,I98,IF($C$11=J$11,J98,IF($C$11=K$11,K98,IF($C$11=L$11,L98,IF($C$11=M$11,M98,N98)))))))) -> 96.53 | E98: 1º Sexenio | F98: 96.53 | G98: =+F98 -> 96.53 | H98: =+G98 -> 96.53 | I98: =+H98 -> 96.53 | J98: =+I98 -> 96.53 | K98: =+J98 -> 96.53 | L98: =+K98 -> 96.53 | M98: =+L98 -> 96.53 | N98: =+M98 -> 96.53 | AB98: 86.88 | AC98: 1º Sexenio
B99: 2º Sexenio | C99: =IF($C$11=$F$11,F99,IF($C$11=G$11,G99,IF($C$11=H$11,H99,IF($C$11=I$11,I99,IF($C$11=J$11,J99,IF($C$11=K$11,K99,IF($C$11=L$11,L99,IF($C$11=M$11,M99,N99)))))))) -> 114.53 | E99: 2º Sexenio | F99: 114.53 | G99: =+F99 -> 114.53 | H99: =+G99 -> 114.53 | I99: =+H99 -> 114.53 | J99: =+I99 -> 114.53 | K99: =+J99 -> 114.53 | L99: =+K99 -> 114.53 | M99: =+L99 -> 114.53 | N99: =+M99 -> 114.53 | AB99: 103.08 | AC99: 2º Sexenio
B100: 3º Sexenio | C100: =IF($C$11=$F$11,F100,IF($C$11=G$11,G100,IF($C$11=H$11,H100,IF($C$11=I$11,I100,IF($C$11=J$11,J100,IF($C$11=K$11,K100,IF($C$11=L$11,L100,IF($C$11=M$11,M100,N100)))))))) -> 143.73 | E100: 3º Sexenio | F100: 143.73 | G100: =+F100 -> 143.73 | H100: =+G100 -> 143.73 | I100: =+H100 -> 143.73 | J100: =+I100 -> 143.73 | K100: =+J100 -> 143.73 | L100: =+K100 -> 143.73 | M100: =+L100 -> 143.73 | N100: =+M100 -> 143.73 | AB100: 129.36 | AC100: 3º Sexenio
B101: 4º Sexenio | C101: =IF($C$11=$F$11,F101,IF($C$11=G$11,G101,IF($C$11=H$11,H101,IF($C$11=I$11,I101,IF($C$11=J$11,J101,IF($C$11=K$11,K101,IF($C$11=L$11,L101,IF($C$11=M$11,M101,N101)))))))) -> 162.77 | E101: 4º Sexenio | F101: 162.77 | G101: =+F101 -> 162.77 | H101: =+G101 -> 162.77 | I101: =+H101 -> 162.77 | J101: =+I101 -> 162.77 | K101: =+J101 -> 162.77 | L101: =+K101 -> 162.77 | M101: =+L101 -> 162.77 | N101: =+M101 -> 162.77 | AB101: 146.49 | AC101: 4º Sexenio
B102: 5º Sexenio | C102: =IF($C$11=$F$11,F102,IF($C$11=G$11,G102,IF($C$11=H$11,H102,IF($C$11=I$11,I102,IF($C$11=J$11,J102,IF($C$11=K$11,K102,IF($C$11=L$11,L102,IF($C$11=M$11,M102,N102)))))))) -> 60.09 | E102: 5º Sexenio | F102: 60.09 | G102: =+F102 -> 60.09 | H102: =+G102 -> 60.09 | I102: =+H102 -> 60.09 | J102: =+I102 -> 60.09 | K102: =+J102 -> 60.09 | L102: =+K102 -> 60.09 | M102: =+L102 -> 60.09 | N102: =+M102 -> 60.09 | AB102: 54.08 | AC102: 5º Sexenio
B103: Tutoría | C103: =IF($C$11=$F$11,F103,IF($C$11=G$11,G103,IF($C$11=H$11,H103,IF($C$11=I$11,I103,IF($C$11=J$11,J103,IF($C$11=K$11,K103,IF($C$11=L$11,L103,IF($C$11=M$11,M103,N103)))))))) -> 0 | E103: Tutoría | G103: =+F103 -> 0 | H103: =+G103 -> 0 | I103: =+H103 -> 0 | J103: =+I103 -> 0 | K103: =+J103 -> 0 | L103: =+K103 -> 0 | M103: =+L103 -> 0
B104: Cargo directivo | C104: =IF($C$11=$F$11,F104,IF($C$11=G$11,G104,IF($C$11=H$11,H104,IF($C$11=I$11,I104,IF($C$11=J$11,J104,IF($C$11=K$11,K104,IF($C$11=L$11,L104,IF($C$11=M$11,M104,N104)))))))) -> 332.96 | E104: Cargo directivo | F104: =IF($C$1=F87,'Nómina mensual'!$D$29,0) -> 0 | G104: =IF($C$1=G87,'Nómina mensual'!$D$29,0) -> 0 | H104: =IF($C$1=H87,'Nómina mensual'!$D$29,0) -> 0 | I104: =IF($C$1=I87,'Nómina mensual'!$D$29,0) -> 332.96 | J104: =IF($C$1=J87,'Nómina mensual'!$D$29,0) -> 0 | K104: =IF($C$1=K87,'Nómina mensual'!$D$29,0) -> 0 | L104: =IF($C$1=L87,'Nómina mensual'!$D$29,0) -> 0 | M104: =IF($C$1=M87,'Nómina mensual'!$D$29,0) -> 0
B105: Residencia Isla Capitalina | C105: =IF($C$11=$F$11,F105,IF($C$11=G$11,G105,IF($C$11=H$11,H105,IF($C$11=I$11,I105,IF($C$11=J$11,J105,IF($C$11=K$11,K105,IF($C$11=L$11,L105,IF($C$11=M$11,M105,N105)))))))) -> 0 | E105: Residencia Isla Capitalina
B106: Residencia Isla No Capitalina | C106: =IF($C$11=$F$11,F106,IF($C$11=G$11,G106,IF($C$11=H$11,H106,IF($C$11=I$11,I106,IF($C$11=J$11,J106,IF($C$11=K$11,K106,IF($C$11=L$11,L106,IF($C$11=M$11,M106,N106)))))))) -> 0 | E106: Residencia Isla No Capitalina
B107: Trienios Residencia Isla No Capitalina | C107: =IF($C$11=$F$11,F107,IF($C$11=G$11,G107,IF($C$11=H$11,H107,IF($C$11=I$11,I107,IF($C$11=J$11,J107,IF($C$11=K$11,K107,IF($C$11=L$11,L107,IF($C$11=M$11,M107,N107)))))))) -> 0 | E107: Trienios Residencia Isla No Capitalina
B108: Adicional maestros 1º y 2º ESO | C108: =IF($C$11=$F$11,F108,IF($C$11=G$11,G108,IF($C$11=H$11,H108,IF($C$11=I$11,I108,IF($C$11=J$11,J108,IF($C$11=K$11,K108,IF($C$11=L$11,L108,IF($C$11=M$11,M108,N108)))))))) -> 0 | E108: Adicional maestros 1º y 2º ESO | F108: 139.7
B109: Complemento mejora/especial dedicación | C109: =IF($C$11=$F$11,F109,IF($C$11=G$11,G109,IF($C$11=H$11,H109,IF($C$11=I$11,I109,IF($C$11=J$11,J109,IF($C$11=K$11,K109,IF($C$11=L$11,L109,IF($C$11=M$11,M109,N109)))))))) -> 0 | E109: Fondos adicionales | O109: FONDOS ADICIONALES
B110: Productividad semestral (Murcia) | C110: =IF($C$11=$F$11,F110,IF($C$11=G$11,G110,IF($C$11=H$11,H110,IF($C$11=I$11,I110,IF($C$11=J$11,J110,IF($C$11=K$11,K110,IF($C$11=L$11,L110,IF($C$11=M$11,M110,N110)))))))) -> 0 | E110: Productividad semestral (Murcia) | F110: =O110/2 -> 0 | G110: =+F110 -> 0 | H110: =+G110 -> 0 | I110: =+H110 -> 0 | J110: =+I110 -> 0 | K110: =+J110 -> 0 | L110: =+K110 -> 0 | M110: =+L110 -> 0 | N110: =+M110 -> 0
B111: Reducción 3% (Castilla la Mancha) | C111: =IF($C$11=$F$11,F111,IF($C$11=G$11,G111,IF($C$11=H$11,H111,IF($C$11=I$11,I111,IF($C$11=J$11,J111,IF($C$11=K$11,K111,IF($C$11=L$11,L111,IF($C$11=M$11,M111,N111)))))))) -> 0 | E111: Reducción 3% (Castilla la Mancha)
B112: Otros | C112: =IF($C$11=$F$11,F112,IF($C$11=G$11,G112,IF($C$11=H$11,H112,IF($C$11=I$11,I112,IF($C$11=J$11,J112,IF($C$11=K$11,K112,IF($C$11=L$11,L112,IF($C$11=M$11,M112,N112)))))))) -> 0 | E112: Otros
...

Sheet DATOS
A1: ARAGÓN: | B1: Tiene importes diferentes en lo ssexenios mensuales, que en los sexenios de las pagas extras
A2: CANARIAS:
A3: BALEARES: | B3: Tienen complemento autonómico para funcionarios en prácticas e interinos, y otro para funcionarios de carrera escalable por antigüedad (como sexenios). También acuerdo de difícil cobertura difrente por islas, y una indemnización por residencia que también cambia en función del grupo profesional (A1, A2)
A4: CANARIAS: | B4: Las extras tienen los sexenios reducidos. El complemento específico en la extra es menor que en las pagas ordinarias. Los trienios en isla no capitalina son menores
A5: CANTABRIA
A6: CASTILLA LA MANCHA:
A7: MADRID: | B7: Los cargos directivos tienen un componente fijo y otro variable en función del número de alumnos matriculados
A8: MURCIA:
A9: NAVARRA: | B9: Antigüedad mediante escala de grados y quinquenios. No tienen complemento de destino. El sueldo base es más alto
